Workbook

Sheet Start Here
B1: ChessLab: complete build and learning plan
B2: From your current static chess AI to a deployed full-stack AI learning app. Every step, every command, every file, and the lesson behind it.
B4: How to use this workbook
B5: 1. Dashboard | C5: Your progress by phase, updated automatically from the Tasks sheet. Set your weekly hours to see an estimated finish.
B6: 2. Tasks | C6: The plan: 178 small steps in 23 phases. Each row says what to do, the exact commands, which code file to use, which lesson explains it, and how you know it is done. Work top to bottom.
B7: 3. Lessons / Lesson Notes | C7: 58 lessons that teach the WHY and HOW behind each step, with self-check questions and free resources. Tasks link straight to the right lesson.
B8: 4. Code Index / Code | C8: Every source file, line by line, ready to copy into the path shown. Tasks link straight to the right file.
B9: 5. API Reference, Config & Env | C9: Every endpoint, environment variable and port in one place.
B10: 6. Checklists | C10: Security, privacy, deployment verification, engineering, AI evidence and portfolio checks for the release.
B11: 7. Troubleshooting | C11: Symptoms, causes and fixes for the problems you are most likely to hit (several were hit for real while preparing this plan).
B12: 8. Glossary, Resources, Interview Prep, Decisions | C12: Look up terms, find all links in one list, practise interview answers, and see how this plan differs from PROJECT_PLAN.md.
B14: What you edit (legend)
B15: Yellow cells | C15: The only cells you edit: Status (dropdown), Date done, My notes on Tasks and Lessons; hours per week on the Dashboard; Done/Practised columns on Checklists and Interview Prep. Blue text = your input.
B16: Status values | C16: Not started · In progress · Done · Skipped · Blocked. Rows colour themselves: green Done, amber In progress, red Blocked, grey Skipped.
B17: Example filled row | C17: Status: Done · Date done: 2026-10-24 · My notes: 'Pushed after a pull --rebase; Docker needed a restart after enabling WSL2.'
B18: Kinds of task | C18: Learn (study a lesson), Setup (install or configure), Build (write code), Test (prove it works), Deploy (put it live), Doc (write for readers).
B19: Core vs Stretch | C19: Core phases G0 and P0-P14 are the portfolio release (blue bands). Stretch phases S1-S7 are optional extras (green bands), fully specified for later.
B20: Owners | C20: Each step is owned by Srikanth (green) or Siva prasad (blue). Both (grey) means each of you does it on your own laptop. Hours are balanced inside every phase; see the team split on the Dashboard.
B21: Git | C21: One shared repository, everyone pushes to main. Before a step: git pull --rebase. After a step that changed files: git add -A, git commit -m "P3.05: ...", git push. Study and install steps have no Git commands.
B22: '→ Code: path' | C22: In the Commands column means: open that file on the Code sheet (the 'Code file' column links to it) and copy it to that path in your repository.
B23: Commands | C23: Written for Git Bash on Windows, on both laptops. Run them from the folder named in the task (usually the repo root, apps/web or services/backend). Docker commands with container paths start with MSYS_NO_PATHCONV=1 on purpose.
B25: What you will build
B26: The product | C26: ChessLab: play chess against an engine in the browser, import your Lichess games, see VERIFIED missed knight forks with the line and material they win, practise the same idea on new puzzles chosen for your level, and track honest progress.
B27: Architecture | C27: Browser (React + TypeScript; Stockfish WASM and your original engine in Web Workers) → FastAPI (validation, guest auth, ownership) → PostgreSQL (all data AND the job queue) ← Python worker (python-chess + native Stockfish: analysis and imports). Hosting: Vercel (frontend), Render (API, worker, Postgres).
B28: Where the AI is | C28: Search (Stockfish, integrated) · rules + verification (your fork detector) · a learner model (per-concept Elo driving adaptive practice) · rigorous evaluation (precision/recall with intervals, calibration) · optional LLM (Claude) that only rewords verified explanations. See lesson L37.
B29: Checkpoints | C29: A (end of P5): a stranger can play a full game on your public URL. B (end of P10): play/import → review → new exercise → graded attempt, live. Release 1.0 (end of P14): measured, documented, portfolio-ready.
B31: How this plan relates to PROJECT_PLAN.md
B32: Same destination, leaner path | C32: It follows the original blueprint but applies the review's recommendations: the game is played in the browser (server re-validates the PGN), and 'done' means the Core phases. Chess.com, hanging pieces, engine comparison, the pilot and ML extensions are fully planned as Stretch phases. Details: Decisions sheet.
B33: Local ports on THIS machine | C33: Other projects already use 5432 (Postgres), 8000 (API) and 5173 (Vite). ChessLab uses 5433 (Postgres), 8010 (API) and 5180 (web). See Config & Env.
B35: What was verified while building this plan
B36: ✓ 1 | C36: Repository (2026-10-22): this folder was initialised on main with a personal identity for this repository only (the global identity is the work account) and connected to github.com/msris93197-dev/ChessLab; access verified with git ls-remote. The first commit and push are step G0.03.
B37: ✓ 2 | C37: Backend: 43 automated tests pass on Python with real PostgreSQL 16: detector logic, grading, Elo, PGN parsing, LLM guards, hanging pieces, plus API integration tests for ownership, idempotency, FOR UPDATE SKIP LOCKED (4 threads × 30 jobs, no duplicates), stale-worker fencing, cancellation, practice flow, deletion and a concurrency regression.
B38: ✓ 3 | C38: Migrations: Alembic autogenerate created all tables from the models; 'alembic check' reported no drift.
B39: ✓ 4 | C39: Docker: the backend image builds and contains Stockfish 15.1; the full Compose stack (db → migrations → API → worker) started and served the app.
B40: ✓ 5 | C40: Real engine: the pipeline found a missed fork with Stockfish and produced a correct explanation; a sample game from low-strength engine self-play gave the public demo (18.Nf7 forking queen and rook).
B41: ✓ 6 | C41: Frontend: TypeScript compiles, Vitest passes, production build succeeds, lint is clean; Playwright in Chromium passed 3 frontend journeys and 2 full-stack journeys (play → resign → background analysis → review → practice → progress, and the public demo).
B42: ✓ 7 | C42: Live providers: the Lichess importer fetched and parsed real public games and handled 'user not found'; a 5-game import ran through the queue end to end; the Chess.com importer (stretch) fetched real games.
B43: ✓ 8 | C43: Bugs found and fixed during verification (now lessons): a get-or-create race exposed by React StrictMode (L30), the knight-vs-rook endgame that correctly produced no finding (L35), psycopg's -1 rowcount on bulk insert, port clashes with other local projects, Git Bash path rewriting.
B44: ✓ 9 | C44: Not verified here (needs your accounts): the actual Render and Vercel deployments, the Claude API call itself (guards are tested; the call needs your key), and the 300 MB puzzle download (the script was tested on a sample).
B45: ✓ 10 | C45: All 192 resource links were checked and resolve.
B47: Time and cost
B48: Estimated effort | C48: ="Core: "&TEXT(Dashboard!H29,"0")&" h planned + "&TEXT(Dashboard!E34,"0%")&" contingency = about "&TEXT(Dashboard!H29*(1+Dashboard!E34),"0")&" h · Stretch: "&TEXT(Dashboard!H30,"0")&" h · Lesson reading (included in Learn tasks): about "&TEXT(Lessons!D62,"0")&" h"
B49: Hosting | C49: Develop locally for free. From Phase 5 you need always-on Render services (web service, background worker, Postgres) because free web services sleep and free databases expire; check current prices at render.com/pricing and set a monthly ceiling. Vercel Hobby is free for personal projects. The optional Claude API (S3) is pay-per-use; set a spending limit.
B50: Honesty rule | C50: Never put a number in the README, Methodology page or your resume that you did not measure. Bracketed placeholders like [N] must be replaced with real values or removed.

Sheet Dashboard
A1: ChessLab progress dashboard
A2: Everything below updates automatically from the Status column of the Tasks sheet. Edit only yellow cells (here: hours per week).
A4: Phase | B4: Name | C4: Type | D4: Checkpoint / goal | E4: Tasks | F4: Done | G4: % done | H4: Est. hrs | I4: Hrs done | J4: Hrs left
A5: G0 | B5: Repository and team setup | C5: Core | D5: Connect this folder to GitHub, make the first push, and get Siva prasad pushing to the same repository. | E5: =COUNTIF(Tasks!$B$2:$B$202,A5) | F5: =COUNTIFS(Tasks!$B$2:$B$202,A5,Tasks!$M$2:$M$202,"Done")+COUNTIFS(Tasks!$B$2:$B$202,A5,Tasks!$M$2:$M$202,"Skipped") | G5: =IF(E5=0,0,F5/E5) | H5: =SUMIF(Tasks!$B$2:$B$202,A5,Tasks!$L$2:$L$202) | I5: =SUMIFS(Tasks!$L$2:$L$202,Tasks!$B$2:$B$202,A5,Tasks!$M$2:$M$202,"Done") | J5: =H5-I5-SUMIFS(Tasks!$L$2:$L$202,Tasks!$B$2:$B$202,A5,Tasks!$M$2:$M$202,"Skipped")
A6: P0 | B6: Orientation and tool setup | C6: Core | D6: Install every tool, create accounts, understand the target architecture. | E6: =COUNTIF(Tasks!$B$2:$B$202,A6) | F6: =COUNTIFS(Tasks!$B$2:$B$202,A6,Tasks!$M$2:$M$202,"Done")+COUNTIFS(Tasks!$B$2:$B$202,A6,Tasks!$M$2:$M$202,"Skipped") | G6: =IF(E6=0,0,F6/E6) | H6: =SUMIF(Tasks!$B$2:$B$202,A6,Tasks!$L$2:$L$202) | I6: =SUMIFS(Tasks!$L$2:$L$202,Tasks!$B$2:$B$202,A6,Tasks!$M$2:$M$202,"Done") | J6: =H6-I6-SUMIFS(Tasks!$L$2:$L$202,Tasks!$B$2:$B$202,A6,Tasks!$M$2:$M$202,"Skipped")
A7: P1 | B7: Understand and preserve the original project | C7: Core | D7: Record what exists, protect it with Git, inventory licences. | E7: =COUNTIF(Tasks!$B$2:$B$202,A7) | F7: =COUNTIFS(Tasks!$B$2:$B$202,A7,Tasks!$M$2:$M$202,"Done")+COUNTIFS(Tasks!$B$2:$B$202,A7,Tasks!$M$2:$M$202,"Skipped") | G7: =IF(E7=0,0,F7/E7) | H7: =SUMIF(Tasks!$B$2:$B$202,A7,Tasks!$L$2:$L$202) | I7: =SUMIFS(Tasks!$L$2:$L$202,Tasks!$B$2:$B$202,A7,Tasks!$M$2:$M$202,"Done") | J7: =H7-I7-SUMIFS(Tasks!$L$2:$L$202,Tasks!$B$2:$B$202,A7,Tasks!$M$2:$M$202,"Skipped")
A8: P2 | B8: Repository scaffold and local database | C8: Core | D8: Monorepo folders, frontend and backend skeletons, Postgres in Docker. | E8: =COUNTIF(Tasks!$B$2:$B$202,A8) | F8: =COUNTIFS(Tasks!$B$2:$B$202,A8,Tasks!$M$2:$M$202,"Done")+COUNTIFS(Tasks!$B$2:$B$202,A8,Tasks!$M$2:$M$202,"Skipped") | G8: =IF(E8=0,0,F8/E8) | H8: =SUMIF(Tasks!$B$2:$B$202,A8,Tasks!$L$2:$L$202) | I8: =SUMIFS(Tasks!$L$2:$L$202,Tasks!$B$2:$B$202,A8,Tasks!$M$2:$M$202,"Done") | J8: =H8-I8-SUMIFS(Tasks!$L$2:$L$202,Tasks!$B$2:$B$202,A8,Tasks!$M$2:$M$202,"Skipped")
A9: P3 | B9: Backend foundations | C9: Core | D9: Settings, database models, migrations, guest sessions, errors, health checks, first tests. | E9: =COUNTIF(Tasks!$B$2:$B$202,A9) | F9: =COUNTIFS(Tasks!$B$2:$B$202,A9,Tasks!$M$2:$M$202,"Done")+COUNTIFS(Tasks!$B$2:$B$202,A9,Tasks!$M$2:$M$202,"Skipped") | G9: =IF(E9=0,0,F9/E9) | H9: =SUMIF(Tasks!$B$2:$B$202,A9,Tasks!$L$2:$L$202) | I9: =SUMIFS(Tasks!$L$2:$L$202,Tasks!$B$2:$B$202,A9,Tasks!$M$2:$M$202,"Done") | J9: =H9-I9-SUMIFS(Tasks!$L$2:$L$202,Tasks!$B$2:$B$202,A9,Tasks!$M$2:$M$202,"Skipped")
A10: P4 | B10: Playable game in the browser | C10: Core | D10: Board, rules, Stockfish WASM opponent, your original engine, promotion, PGN export. | E10: =COUNTIF(Tasks!$B$2:$B$202,A10) | F10: =COUNTIFS(Tasks!$B$2:$B$202,A10,Tasks!$M$2:$M$202,"Done")+COUNTIFS(Tasks!$B$2:$B$202,A10,Tasks!$M$2:$M$202,"Skipped") | G10: =IF(E10=0,0,F10/E10) | H10: =SUMIF(Tasks!$B$2:$B$202,A10,Tasks!$L$2:$L$202) | I10: =SUMIFS(Tasks!$L$2:$L$202,Tasks!$B$2:$B$202,A10,Tasks!$M$2:$M$202,"Done") | J10: =H10-I10-SUMIFS(Tasks!$L$2:$L$202,Tasks!$B$2:$B$202,A10,Tasks!$M$2:$M$202,"Skipped")
A11: P5 | B11: First public deployment (thin slice) | C11: Core | D11: Checkpoint A: a stranger can play a complete game on the public URL | E11: =COUNTIF(Tasks!$B$2:$B$202,A11) | F11: =COUNTIFS(Tasks!$B$2:$B$202,A11,Tasks!$M$2:$M$202,"Done")+COUNTIFS(Tasks!$B$2:$B$202,A11,Tasks!$M$2:$M$202,"Skipped") | G11: =IF(E11=0,0,F11/E11) | H11: =SUMIF(Tasks!$B$2:$B$202,A11,Tasks!$L$2:$L$202) | I11: =SUMIFS(Tasks!$L$2:$L$202,Tasks!$B$2:$B$202,A11,Tasks!$M$2:$M$202,"Done") | J11: =H11-I11-SUMIFS(Tasks!$L$2:$L$202,Tasks!$B$2:$B$202,A11,Tasks!$M$2:$M$202,"Skipped")
A12: P6 | B12: Saving games and the durable job queue | C12: Core | D12: Server re-validates games; Postgres queue with leases; the worker process with Stockfish. | E12: =COUNTIF(Tasks!$B$2:$B$202,A12) | F12: =COUNTIFS(Tasks!$B$2:$B$202,A12,Tasks!$M$2:$M$202,"Done")+COUNTIFS(Tasks!$B$2:$B$202,A12,Tasks!$M$2:$M$202,"Skipped") | G12: =IF(E12=0,0,F12/E12) | H12: =SUMIF(Tasks!$B$2:$B$202,A12,Tasks!$L$2:$L$202) | I12: =SUMIFS(Tasks!$L$2:$L$202,Tasks!$B$2:$B$202,A12,Tasks!$M$2:$M$202,"Done") | J12: =H12-I12-SUMIFS(Tasks!$L$2:$L$202,Tasks!$B$2:$B$202,A12,Tasks!$M$2:$M$202,"Skipped")
A13: P7 | B13: Importing history: Lichess and PGN upload | C13: Core | D13: Streaming provider import, dedupe, progress, cancellation, upload validation. | E13: =COUNTIF(Tasks!$B$2:$B$202,A13) | F13: =COUNTIFS(Tasks!$B$2:$B$202,A13,Tasks!$M$2:$M$202,"Done")+COUNTIFS(Tasks!$B$2:$B$202,A13,Tasks!$M$2:$M$202,"Skipped") | G13: =IF(E13=0,0,F13/E13) | H13: =SUMIF(Tasks!$B$2:$B$202,A13,Tasks!$L$2:$L$202) | I13: =SUMIFS(Tasks!$L$2:$L$202,Tasks!$B$2:$B$202,A13,Tasks!$M$2:$M$202,"Done") | J13: =H13-I13-SUMIFS(Tasks!$L$2:$L$202,Tasks!$B$2:$B$202,A13,Tasks!$M$2:$M$202,"Skipped")
A14: P8 | B14: Tactical analysis: verified missed knight forks | C14: Core | D14: Candidate generation, engine verification, evidence records, negative tests. | E14: =COUNTIF(Tasks!$B$2:$B$202,A14) | F14: =COUNTIFS(Tasks!$B$2:$B$202,A14,Tasks!$M$2:$M$202,"Done")+COUNTIFS(Tasks!$B$2:$B$202,A14,Tasks!$M$2:$M$202,"Skipped") | G14: =IF(E14=0,0,F14/E14) | H14: =SUMIF(Tasks!$B$2:$B$202,A14,Tasks!$L$2:$L$202) | I14: =SUMIFS(Tasks!$L$2:$L$202,Tasks!$B$2:$B$202,A14,Tasks!$M$2:$M$202,"Done") | J14: =H14-I14-SUMIFS(Tasks!$L$2:$L$202,Tasks!$B$2:$B$202,A14,Tasks!$M$2:$M$202,"Skipped")
A15: P9 | B15: Explanations, review screen and public demo | C15: Core | D15: Deterministic templates, replayable evidence, precomputed demo. | E15: =COUNTIF(Tasks!$B$2:$B$202,A15) | F15: =COUNTIFS(Tasks!$B$2:$B$202,A15,Tasks!$M$2:$M$202,"Done")+COUNTIFS(Tasks!$B$2:$B$202,A15,Tasks!$M$2:$M$202,"Skipped") | G15: =IF(E15=0,0,F15/E15) | H15: =SUMIF(Tasks!$B$2:$B$202,A15,Tasks!$L$2:$L$202) | I15: =SUMIFS(Tasks!$L$2:$L$202,Tasks!$B$2:$B$202,A15,Tasks!$M$2:$M$202,"Done") | J15: =H15-I15-SUMIFS(Tasks!$L$2:$L$202,Tasks!$B$2:$B$202,A15,Tasks!$M$2:$M$202,"Skipped")
A16: P10 | B16: Puzzle dataset and targeted practice | C16: Core | D16: Checkpoint B: play/import -> review -> new exercise -> graded attempt, live | E16: =COUNTIF(Tasks!$B$2:$B$202,A16) | F16: =COUNTIFS(Tasks!$B$2:$B$202,A16,Tasks!$M$2:$M$202,"Done")+COUNTIFS(Tasks!$B$2:$B$202,A16,Tasks!$M$2:$M$202,"Skipped") | G16: =IF(E16=0,0,F16/E16) | H16: =SUMIF(Tasks!$B$2:$B$202,A16,Tasks!$L$2:$L$202) | I16: =SUMIFS(Tasks!$L$2:$L$202,Tasks!$B$2:$B$202,A16,Tasks!$M$2:$M$202,"Done") | J16: =H16-I16-SUMIFS(Tasks!$L$2:$L$202,Tasks!$B$2:$B$202,A16,Tasks!$M$2:$M$202,"Skipped")
... A27: S7 | B27: Stretch: production extras | C27: Stretch | D27: Error tracking, separate workers, accounts that claim guest data. | E27: =COUNTIF(Tasks!$B$2:$B$202,A27) | F27: =COUNTIFS(Tasks!$B$2:$B$202,A27,Tasks!$M$2:$M$202,"Done")+COUNTIFS(Tasks!$B$2:$B$202,A27,Tasks!$M$2:$M$202,"Skipped") | G27: =IF(E27=0,0,F27/E27) | H27: =SUMIF(Tasks!$B$2:$B$202,A27,Tasks!$L$2:$L$202) | I27: =SUMIFS(Tasks!$L$2:$L$202,Tasks!$B$2:$B$202,A27,Tasks!$M$2:$M$202,"Done") | J27: =H27-I27-SUMIFS(Tasks!$L$2:$L$202,Tasks!$B$2:$B$202,A27,Tasks!$M$2:$M$202,"Skipped")
B29: Core (G0, P0-P14) | E29: =SUMIF(C5:C27,"Core",E5:E27) | F29: =SUMIF(C5:C27,"Core",F5:F27) | G29: =IF(E29=0,0,F29/E29) | H29: =SUMIF(C5:C27,"Core",H5:H27) | I29: =SUMIF(C5:C27,"Core",I5:I27) | J29: =H29-I29
B30: Stretch (S1-S7) | E30: =SUMIF(C5:C27,"Stretch",E5:E27) | F30: =SUMIF(C5:C27,"Stretch",F5:F27) | G30: =IF(E30=0,0,F30/E30) | H30: =SUMIF(C5:C27,"Stretch",H5:H27) | I30: =SUMIF(C5:C27,"Stretch",I5:I27) | J30: =H30-I30
B31: All phases | E31: =E29+E30 | F31: =F29+F30 | G31: =IF(E31=0,0,F31/E31) | H31: =H29+H30 | I31: =I29+I30 | J31: =J29+J30
B33: Your hours per week (edit) | E33: 12 | F33: ← assumption: change to your real weekly time
B34: Debugging / rework contingency (edit) | E34: 0.3 | F34: ← assumption: beginners usually need 25-50% extra for debugging and rework
B35: Weeks left for Core at that pace | E35: =IF(E33=0,0,J29*(1+E34)/E33)
B36: Weeks left for everything | E36: =IF(E33=0,0,J31*(1+E34)/E33)
B37: Lessons completed | E37: =COUNTIF(Lessons!F2:F60,"Done") | F37: =COUNTIF(Lessons!A2:A60,"*") | G37: =IF(F37=0,0,E37/F37)
B39: Team split (Both counts for each person) | E39: Steps | F39: Done | G39: % done | H39: Est. hrs | I39: Hrs done | J39: Hrs left
B40: Srikanth | E40: =COUNTIF(Tasks!$C$2:$C$202,"Srikanth")+COUNTIF(Tasks!$C$2:$C$202,"Both") | F40: =COUNTIFS(Tasks!$C$2:$C$202,"Srikanth",Tasks!$M$2:$M$202,"Done")+COUNTIFS(Tasks!$C$2:$C$202,"Both",Tasks!$M$2:$M$202,"Done") | G40: =IF(E40=0,0,F40/E40) | H40: =SUMIF(Tasks!$C$2:$C$202,"Srikanth",Tasks!$L$2:$L$202)+SUMIF(Tasks!$C$2:$C$202,"Both",Tasks!$L$2:$L$202) | I40: =SUMIFS(Tasks!$L$2:$L$202,Tasks!$C$2:$C$202,"Srikanth",Tasks!$M$2:$M$202,"Done")+SUMIFS(Tasks!$L$2:$L$202,Tasks!$C$2:$C$202,"Both",Tasks!$M$2:$M$202,"Done") | J40: =H40-I40
B41: Siva prasad | E41: =COUNTIF(Tasks!$C$2:$C$202,"Siva prasad")+COUNTIF(Tasks!$C$2:$C$202,"Both") | F41: =COUNTIFS(Tasks!$C$2:$C$202,"Siva prasad",Tasks!$M$2:$M$202,"Done")+COUNTIFS(Tasks!$C$2:$C$202,"Both",Tasks!$M$2:$M$202,"Done") | G41: =IF(E41=0,0,F41/E41) | H41: =SUMIF(Tasks!$C$2:$C$202,"Siva prasad",Tasks!$L$2:$L$202)+SUMIF(Tasks!$C$2:$C$202,"Both",Tasks!$L$2:$L$202) | I41: =SUMIFS(Tasks!$L$2:$L$202,Tasks!$C$2:$C$202,"Siva prasad",Tasks!$M$2:$M$202,"Done")+SUMIFS(Tasks!$L$2:$L$202,Tasks!$C$2:$C$202,"Both",Tasks!$M$2:$M$202,"Done") | J41: =H41-I41
B44: Notes
B45: Estimated hours are planning guesses for someone new to backend and AI work, including study time ('Learn' tasks contain the lesson reading). Re-estimate after Checkpoint A.
B46: 'Skipped' tasks count as finished for % done but not as hours done.
B47: Checkpoint A (end of P5): public playable game. Checkpoint B (end of P10): complete learning loop live. Release 1.0 (end of P14): portfolio-ready.

Sheet Tasks
A1: ID | B1: Phase | C1: Owner | D1: Kind | E1: Task | F1: How to do it (step by step) | G1: Commands / code to use (Git Bash) | H1: Git: before you start / save your work | I1: Code file | J1: Lessons | K1: Done when | L1: Est. hrs | M1: Status (edit) | N1: Date done (edit) | O1: My notes (edit)
E2: G0 Repository and team setup (Core) | F2: Connect this folder to GitHub, make the first push, and get Siva prasad pushing to the same repository.
A3: G0.01 | B3: G0 | C3: Srikanth | D3: Setup | E3: Check your GitHub login | F3: 1. Open Git Bash (or the VS Code terminal once it is set to Git Bash in P0.03). 2. Check that gh is logged in and that msris93197-dev is the ACTIVE account. This laptop is also logged in as srikanth-qaig (work), and pushes use whichever account is active. 3. Let git use gh for GitHub credentials (already set up on this laptop; running it again is harmless). | G3: gh auth status gh auth switch -u msris93197-dev # only if the work account is active gh auth setup-git | J3: L02 | K3: gh auth status shows msris93197-dev as the active account. | L3: 0.25 | M3: Not started
A4: G0.02 | B4: G0 | C4: Srikanth | D4: Setup | E4: Connect this folder to GitHub (done on 2026-10-22) | F4: Already done. For the record: 1. The folder was turned into a Git repository with main as the branch. 2. Your global Git identity is your work account, so this repository got its own identity (msris93197-dev with your private GitHub noreply email). It applies only inside this folder. 3. origin points to https://github.com/msris93197-dev/ChessLab.git. The commands below are the recipe if you ever need to redo it on another laptop. | G4: git init -b main git config user.name "msris93197-dev" git config user.email "280372735+msris93197-dev@users.noreply.github.com" git remote add origin https://github.com/msris93197-dev/ChessLab.git git remote -v | J4: L03 | K4: git remote -v shows the ChessLab URL. | L4: 0.25 | M4: Not started
A5: G0.03 | B5: G0 | C5: Srikanth | D5: Setup | E5: First commit and push (done on 2026-10-22) | F5: Already done: the .gitignore below, the original app and the plan files (in docs/) were committed, pushed to main and tagged original-app. | G5: → Code: .gitignore git add -A git commit -m "Import original chess AI and project plan" git push -u origin main git tag original-app && git push origin original-app | I5: C01 | J5: L03 | K5: GitHub shows the files and the tag original-app. | L5: 0.5 | M5: Not started
A6: G0.04 | B6: G0 | C6: Srikanth | D6: Setup | E6: Invite Siva prasad (done on 2026-10-22) | F6: Already done: satya-siva-prasad-yanamadala was invited with write access. He accepts it in G0.06. | G6: gh api -X PUT repos/msris93197-dev/ChessLab/collaborators/satya-siva-prasad-yanamadala -f permission=push gh api repos/msris93197-dev/ChessLab/invitations --jq '.[].invitee.login' | J6: L03 | K6: The invitation shows as pending (or accepted) for satya-siva-prasad-yanamadala. | L6: 0.25 | M6: Not started
A7: G0.05 | B7: G0 | C7: Srikanth | D7: Setup | E7: Switch to the simple workflow (undo the extra setup from the earlier plan) | F7: An earlier version of this plan added a journal file per step, a protected main branch and per-repo team settings. For two people that is overhead, so remove it: 1. Turn off branch protection, so both of you can push straight to main. 2. Delete the docs/journal folder. git log already records who did what and when. 3. Remove the two chesslab.* settings from this repository (nothing uses them any more). 4. Commit and push. | G7: gh api -X DELETE repos/msris93197-dev/ChessLab/branches/main/protection git pull --rebase git rm -r docs/journal git config --unset chesslab.me; git config --unset chesslab.partner git commit -m "G0.05: Remove journal folder, use a simple push-to-main workflow" git push | J7: L03 | K7: git push succeeds directly to main, and docs/journal is gone on GitHub. | L7: 0.25 | M7: Not started
A8: G0.06 | B8: G0 | C8: Siva prasad | D8: Setup | E8: Set up your laptop, accept the invitation and clone | F8: 1. Install Git for Windows (it includes Git Bash) and the GitHub CLI. Other tools come in chapter P0, where install steps are marked Both. 2. In Git Bash, log in with gh using your GitHub account (satya-siva-prasad-yanamadala) and let git use it. 3. Accept the invitation (or click the link in the invitation email). 4. Clone the repository. 5. Inside the clone, set your name and your GitHub noreply email (GitHub > Settings > Emails) so commits show up under your account. 6. Prove you can push: add yourself to the README and push. | G8: winget install --id Git.Git -e winget install --id GitHub.cli -e gh auth login # GitHub.com > HTTPS > log in with a web browser gh auth setup-git gh api user/repository_invitations --jq '.[] | "\(.id) \(.repository.full_name)"' gh api -X PATCH user/repository_invitations/INVITATION_ID mkdir -p ~/projects && cd ~/projects gh repo clone msris93197-dev/ChessLab && cd ChessLab git config user.name "Siva prasad" git config user.email "YOUR_ID+satya-siva-prasad-yanamadala@users.noreply.github.com" printf '\nBuilt by Srikanth and Siva prasad.\n' >> README.md git add README.md && git commit -m "G0.06: Add team to README" && git push | J8: L02, L03, L59 | K8: Your README commit is visible on GitHub under your name. | L8: 1 | M8: Not started
E9: P0 Orientation and tool setup (Core) | F9: Install every tool, create accounts, understand the target architecture.
A10: P0.01 | B10: P0 | C10: Srikanth | D10: Learn | E10: Read the Start Here sheet and the architecture summary | F10: 1. Read the Start Here sheet fully (10 min). 2. Read lesson L37 (what 'AI' means here) so you can describe the project honestly from day one. 3. Skim the Phase list on the Dashboard: Core phases P0-P14 are the portfolio release; S1-S7 are optional. 4. In a notebook, write the one-sentence pitch in your own words. | J10: L37 | K10: You can explain the 4 runtime parts (browser app, API, worker, Postgres) and what each does. | L10: 0.5 | M10: Not started
A11: P0.02 | B11: P0 | C11: Srikanth | D11: Learn | E11: Learn the web basics | F11: Study lesson L01. Open any website, press F12 > Network, reload, click a request and identify method, URL, status, request headers and response body. | J11: L01 | K11: You can name the parts of an HTTP request/response from a real example. | L11: 1.5 | M11: Not started
A12: P0.03 | B12: P0 | C12: Both | D12: Setup | E12: Install Git for Windows and make Git Bash your terminal | F12: 1. Git is already installed on Srikanth's laptop (git version 2.50). Siva prasad installed it in G0.06. 2. Make Git Bash the default terminal in VS Code: Ctrl+Shift+P > 'Terminal: Select Default Profile' > Git Bash. Every command in this manual is written for Git Bash. 3. Do not set a global name or email for ChessLab: each of you set it inside the repository (G0.02, G0.06). Srikanth's global identity stays the work account for work projects. | G12: git --version git config --local --get-regexp 'user\.' # run inside the ChessLab folder | J12: L03 | K12: VS Code opens Git Bash by default and git config --local shows your personal identity. | L12: 0.25 | M12: Not started
A13: P0.04 | B13: P0 | C13: Siva prasad | D13: Learn | E13: Learn the terminal: Git Bash on Windows | F13: Study lesson L02. In Git Bash practise: cd /d/my_learning/Chess-AI (Srikanth) or cd ~/projects/ChessLab (Siva prasad), pwd, ls -la, export TEST=hi, echo $TEST, cat README.md, history. | J13: L02 | K13: You can move between folders and set an environment variable for one session in Git Bash. | L13: 1 | M13: Not started
A14: P0.05 | B14: P0 | C14: Both | D14: Setup | E14: Install VS Code extensions | F14: Install in VS Code: Python (Microsoft), Pylance, Ruff, ESLint (optional), Prettier (optional), Docker, Playwright Test for VSCode, GitLens (optional), Even Better TOML, Rainbow CSV (helps labelling in P12). | G14: code --install-extension ms-python.python code --install-extension charliermarsh.ruff code --install-extension ms-azuretools.vscode-docker code --install-extension ms-playwright.playwright code --install-extension tamasfe.even-better-toml code --install-extension mechatroniks.rainbow-csv | K14: Extensions visible in the Extensions panel. | L14: 0.25 | M14: Not started
A15: P0.06 | B15: P0 | C15: Both | D15: Setup | E15: Install Node.js LTS | F15: Node 22 is already installed here (node v22). Check with node --version and npm --version. If you ever need another version, use nvm-windows. Node runs Vite, Vitest and Playwright. | G15: node --version npm --version | J15: L04 | K15: node --version prints v22 or newer. | L15: 0.25 | M15: Not started
A16: P0.07 | B16: P0 | C16: Both | D16: Setup | E16: Install uv and a project Python (3.12) | F16: 1. uv is already installed on Srikanth's laptop (~/.local/bin/uv). Each of you checks with uv --version. 2. If it is missing, install it with the official installer (the first command runs Windows' installer from Git Bash), or with winget. 3. Close and reopen Git Bash so the new PATH is picked up. 4. Install Python 3.12 managed by uv (3.14 is very new; 3.12 has the widest library support). | G16: uv --version || powershell.exe -ExecutionPolicy ByPass -c "irm https://astral.sh/uv/install.ps1 | iex" # alternative: winget install --id astral-sh.uv -e uv python install 3.12 uv python list | J16: L04, L11 | K16: uv --version works and 'uv python list' shows a 3.12 interpreter. | L16: 0.5 | M16: Not started
A17: P0.08 | B17: P0 | C17: Both | D17: Setup | E17: Install Docker Desktop with WSL2 | F17: 1. Docker 29 is already installed here. Open Docker Desktop and make sure it says 'Engine running'. 2. Settings > General: 'Use the WSL 2 based engine' is on. Settings > Resources: at least 4 GB memory. 3. Test with hello-world. 4. IMPORTANT for this machine: other projects already use ports 5432, 5434, 8000, 8080 and 5173. ChessLab therefore uses 5433 (Postgres), 8010 (API) and 5180 (web). | G17: docker --version docker run --rm hello-world docker ps --format "{{.Names}} {{.Ports}}" | J17: L15 | K17: hello-world prints its welcome message; you know which ports are already taken. | L17: 0.5 | M17: Not started
A18: P0.09 | B18: P0 | C18: Both | D18: Setup | E18: Create the accounts you will need | F18: Create (free) accounts: GitHub (you have one: srikanth-qaig), Vercel (sign in with GitHub), Render (sign in with GitHub), Lichess (to test imports with your own games). Optional later: Anthropic Console (stretch S3 only). Do NOT create paid resources yet. | J18: L48 | K18: You can log in to GitHub, Vercel and Render with your GitHub identity. | L18: 0.5 | M18: Not started
A19: P0.10 | B19: P0 | C19: Srikanth | D19: Learn | E19: Decide your hosting budget | F19: Open render.com/pricing and vercel.com/pricing. Note the current price of: Render web service (always-on, smallest), background worker, Postgres (smallest paid). Vercel Hobby is free for personal projects. Write a monthly ceiling (for example US$20-25) in your notebook. You can develop for weeks locally before paying anything; you only need paid Render plans from Phase 5 onwards (free plans sleep and free databases expire). | J19: L48 | K19: A written monthly budget and the plan names you will use. | L19: 0.5 | M19: Not started
A20: P0.11 | B20: P0 | C20: Siva prasad | D20: Learn | E20: Learn Git fundamentals | F20: Study lesson L03. Do the first 4 levels of learngitbranching.js.org. | J20: L03 | K20: You can create a branch, commit, and merge it locally. | L20: 1.5 | M20: Not started
E21: P1 Understand and preserve the original project (Core) | F21: Record what exists, protect it with Git, inventory licences.
A22: P1.01 | B22: P1 | C22: Siva prasad | D22: Learn | E22: Run the original app and record its behaviour | F22: 1. Open D:\my_learning\Chess-AI\index.html in a browser (double-click, or VS Code 'Live Server'). 2. Try every control: start, undo, redo, depth selectors, opening buttons (Ruy Lopez, Italian, Sicilian), computer vs computer, hint. 3. Note what works and any bugs (for example: promotion always becomes a queen; long thinking freezes the page at depth 4+). 4. Save notes in docs/baseline-notes.md (create the docs folder). | J22: L10 | K22: docs/baseline-notes.md lists working features, known defects and 3 sample positions (FENs) you tested. | L22: 1 | M22: Not started
A23: P1.02 | B23: P1 | C23: Srikanth | D23: Learn | E23: Understand your original engine | F23: Read js/main.js lines 35-309 with lesson L10 open: weights, pst_w/pst_b (piece-square tables), evaluateBoard (incremental evaluation), minimax with alpha-beta. Write 5 bullet points in baseline-notes.md: how evaluation works, why moves are shuffled, what alpha/beta do, why there is no quiescence search, why promotions are forced to queen. | J23: L10 | K23: You can explain your engine's search and evaluation in 2 minutes. | L23: 2 | M23: Not started
A24: P1.03 | B24: P1 | C24: Srikanth | D24: Setup | E24: Confirm the safety tag on GitHub | F24: The original app was tagged original-app in G0.03. Confirm the tag is on GitHub and that you can look at the old app, then come back to main. | G24: git fetch --tags git ls-remote --tags origin git switch --detach original-app && ls && git switch - | H24: BEFORE YOU START git pull --rebase SAVE YOUR WORK git add -A git status # nothing listed? then there is nothing to commit for this step git commit -m "P1.03: Confirm the safety tag on GitHub" git push # rejected? git pull --rebase, then git push again | J24: L03 | K24: git ls-remote --tags origin lists refs/tags/original-app. | L24: 0.5 | M24: Not started
A25: P1.04 | B25: P1 | C25: Siva prasad | D25: Doc | E25: Create a licence inventory | F25: 1. List third-party parts of the original app: js/chess.js (BSD-2, from chess.js 0.x), chessboard.js 1.0 (MIT, from unpkg), jQuery, Bootstrap 4, Font Awesome kit, piece images in img/chesspieces/wikipedia (Wikimedia origin), piece-square tables adapted from Sunfish (GPLv3, see the comment in main.js). 2. Start docs/THIRD_PARTY_NOTICES.md from the template (Code sheet). 3. Decide your repository licence. Recommended: GPLv3 (compatible with Stockfish, python-chess and Sunfish). Add a LICENSE file (GitHub > Add file > Create new file > name LICENSE > 'Choose a license template'). | G25: → Code: docs/THIRD_PARTY_NOTICES_TEMPLATE.md | H25: BEFORE YOU START git pull --rebase SAVE YOUR WORK git add -A git status # nothing listed? then there is nothing to commit for this step git commit -m "P1.04: Create a licence inventory" git push # rejected? git pull --rebase, then git push again | I25: C83 | J25: L55 | K25: LICENSE and docs/THIRD_PARTY_NOTICES.md exist in the repo. | L25: 1 | M25: Not started
A26: P1.05 | B26: P1 | C26: Siva prasad | D26: Doc | E26: Write acceptance stories | F26: Turn the visitor journey into testable sentences in docs/acceptance.md. Examples: - A guest choosing Black sees a legal engine opening move and can reply without refreshing. - After resigning, 'Review game' opens a review that shows analysis coverage. - A missed fork shows the alternative move, the line, the material gain and a 'Practice this idea' button. - Practising gives a different position; the solution is never sent to the browser. - A second guest cannot read the first guest's games or jobs. - 'Delete my data' makes the old token stop working. Write 15-25 such stories; each later task's 'Done when' should map to one. | H26: BEFORE YOU START git pull --rebase SAVE YOUR WORK git add -A git status # nothing listed? then there is nothing to commit for this step git commit -m "P1.05: Write acceptance stories" git push # rejected? git pull --rebase, then git push again | J26: L23 | K26: docs/acceptance.md with at least 15 stories. | L26: 1 | M26: Not started
A27: P1.06 | B27: P1 | C27: Srikanth | D27: Setup | E27: Agree who does what for the next chapters | F27: 1. Look at the owner labels for P2-P4 and swap any step one of you would rather do, keeping hours roughly even. 2. Agree the habit for every step: git pull --rebase before you start, commit and push when it works. Push small and often so you rarely clash. | G27: git log --oneline -5 | H27: BEFORE YOU START git pull --rebase SAVE YOUR WORK git add -A git status # nothing listed? then there is nothing to commit for this step git commit -m "P1.06: Agree who does what for the next chapters" git push # rejected? git pull --rebase, then git push again | J27: L03 | K27: You both know which P2-P4 steps are yours. | L27: 0.1 | M27: Not started
E28: P2 Repository scaffold and local database (Core) | F28: Monorepo folders, frontend and backend skeletons, Postgres in Docker.
A29: P2.01 | B29: P2 | C29: Srikanth | D29: Setup | E29: Create the folder structure | F29: Create the monorepo layout. Keep the original files in the root for now (they are your baseline; you remove them only after Phase 4 has parity). | G29: mkdir -p apps services data/manifests evaluation/labels evaluation/reports docs/decisions ops .github/workflows ls | H29: BEFORE YOU START git pull --rebase SAVE YOUR WORK git add -A git status # nothing listed? then there is nothing to commit for this step git commit -m "P2.01: Create the folder structure" git push # rejected? git pull --rebase, then git push again | J29: L11 | K29: The folders exist next to index.html, js/, css/. | L29: 0.25 | M29: Not started
A30: P2.02 | B30: P2 | C30: Srikanth | D30: Build | E30: Add the root .gitignore | F30: Create .gitignore in the repo root with the content from the Code sheet. It keeps node_modules, .venv, caches, .env files and big data dumps out of Git. | G30: → Code: .gitignore | H30: BEFORE YOU START git pull --rebase SAVE YOUR WORK git add -A git status # nothing listed? then there is nothing to commit for this step git commit -m "P2.02: Add the root .gitignore" git push # rejected? git pull --rebase, then git push again | I30: C01 | J30: L03, L18 | K30: git status does not show node_modules or .venv after later installs. | L30: 0.1 | M30: Not started
A31: P2.03 | B31: P2 | C31: Srikanth | D31: Build | E31: Scaffold the React + TypeScript app with Vite | F31: 1. From the repo root create apps/web with the official template. 2. Install and run it once. 3. Replace vite.config.ts with the Code sheet version (fixes port 5180). 4. Open http://localhost:5180: you should see the Vite + React page. | G31: → Code: apps/web/vite.config.ts cd apps npm create vite@latest web -- --template react-ts cd web npm install # replace vite.config.ts (Code sheet), then: npm run dev | H31: BEFORE YOU START git pull --rebase SAVE YOUR WORK git add -A git status # nothing listed? then there is nothing to commit for this step git commit -m "P2.03: Scaffold the React + TypeScript app with Vite" git push # rejected? git pull --rebase, then git push again | I31: C16 | J31: L07, L06 | K31: The Vite starter page loads on http://localhost:5180. | L31: 0.5 | M31: Not started
A32: P2.04 | B32: P2 | C32: Srikanth | D32: Setup | E32: Install the frontend libraries (pinned majors) | F32: Install chess rules, the board, routing and the Stockfish WASM build. Pin the major versions this plan was verified with: chess.js 1.x, react-chessboard 4.x (v5 has a different API), react-router-dom 6.x. Then add test tools. | G32: cd apps/web npm install chess.js@1 react-chessboard@4 react-router-dom@6 stockfish npm install -D vitest @playwright/test npx playwright install chromium | H32: BEFORE YOU START git pull --rebase SAVE YOUR WORK git add -A git status # nothing listed? then there is nothing to commit for this step git commit -m "P2.04: Install the frontend libraries" git push # rejected? git pull --rebase, then git push again | J32: L04 | K32: package.json lists chess.js ^1, react-chessboard ^4, react-router-dom ^6, stockfish; package-lock.json exists. | L32: 0.5 | M32: Not started
A33: P2.05 | B33: P2 | C33: Srikanth | D33: Setup | E33: Create the Python backend project with uv | F33: 1. Create services/backend as a uv project on Python 3.12. 2. Add runtime and dev dependencies (uv writes pyproject.toml and uv.lock). 3. Create the package folders with empty __init__.py files? Not required (namespace packages work) but recommended for tooling: app/, app/api, app/analysis, app/domain, app/explain, app/importers, app/jobs, app/learning, app/practice, tests/. 4. Add the [tool.pytest.ini_options] and [tool.ruff] sections from the Code sheet's pyproject.toml. 5. Delete the sample main.py (or hello.py) that uv init created: the real entry point is app/main.py. | G33: → Code: services/backend/pyproject.toml cd services uv init backend --python 3.12 --no-workspace cd backend uv add fastapi "uvicorn[standard]" sqlalchemy "psycopg[binary]" alembic pydantic-settings chess httpx python-multipart uv add --dev pytest ruff zstandard mkdir -p app/{api,analysis,domain,explain,importers,jobs,learning,practice} tests touch app/__init__.py app/{api,analysis,domain,explain,importers,jobs,learning,practice}/__init__.py rm -f main.py hello.py | H33: BEFORE YOU START git pull --rebase SAVE YOUR WORK git add -A git status # nothing listed? then there is nothing to commit for this step git commit -m "P2.05: Create the Python backend project with uv" git push # rejected? git pull --rebase, then git push again | I33: C03 | J33: L11, L04 | K33: uv run python -c "import fastapi, chess, sqlalchemy; print('ok')" prints ok. | L33: 0.75 | M33: Not started
A34: P2.06 | B34: P2 | C34: Srikanth | D34: Setup | E34: Start Postgres with Docker Compose | F34: 1. Put compose.yaml (Code sheet) in the repo root. For now you only start the db service. 2. Start it and check it is healthy. 3. Connect with psql inside the container and run SELECT version(); | G34: → Code: compose.yaml docker compose up -d db docker compose ps docker compose exec db psql -U chesslab -d chesslab -c "SELECT version();" | H34: BEFORE YOU START git pull --rebase SAVE YOUR WORK git add -A git status # nothing listed? then there is nothing to commit for this step git commit -m "P2.06: Start Postgres with Docker Compose" git push # rejected? git pull --rebase, then git push again | I34: C02 | J34: L15, L26 | K34: docker compose ps shows db as healthy on port 5433. | L34: 0.5 | M34: Not started
A35: P2.07 | B35: P2 | C35: Siva prasad | D35: Learn | E35: Learn SQL basics on the real database | F35: Study lesson L14. In psql, create a scratch table, insert, select, update, delete, then drop it. Try a UNIQUE constraint violation on purpose and read the error. | G35: docker compose exec -T db psql -U chesslab -d chesslab <<'SQL' CREATE TABLE scratch (id int PRIMARY KEY, name text UNIQUE); INSERT INTO scratch VALUES (1, 'a'); INSERT INTO scratch VALUES (2, 'a'); -- fails: unique violation (on purpose) INSERT INTO scratch VALUES (2, 'a') ON CONFLICT DO NOTHING; -- no error, nothing inserted SELECT * FROM scratch; DROP TABLE scratch; SQL # to explore by hand instead: winpty docker compose exec db psql -U chesslab -d chesslab | J35: L14 | K35: You have seen a unique violation and ON CONFLICT DO NOTHING behave differently. | L35: 3 | M35: Not started
A36: P2.08 | B36: P2 | C36: Srikanth | D36: Setup | E36: Commit the scaffold | F36: Before this commit, make sure no node_modules, .venv or .env files would be committed. | G36: git status --short | grep -E 'node_modules|\.venv|\.env$' && echo 'STOP: remove these before committing' || echo 'clean' | H36: BEFORE YOU START git pull --rebase SAVE YOUR WORK git add -A git status # nothing listed? then there is nothing to commit for this step git commit -m "P2.08: Commit the scaffold" git push # rejected? git pull --rebase, then git push again | J36: L03 | K36: A clean commit with apps/web, services/backend, compose.yaml. | L36: 0.1 | M36: Not started
E37: P3 Backend foundations (Core) | F37: Settings, database models, migrations, guest sessions, errors, health checks, first tests.
A38: P3.01 | B38: P3 | C38: Siva prasad | D38: Learn | E38: Learn FastAPI basics | F38: Study lesson L13 and do the first 6 pages of the official FastAPI tutorial in a scratch file (not in the project). | J38: L12, L13 | K38: You wrote and called a scratch endpoint with a Pydantic body. | L38: 5 | M38: Not started
A39: P3.02 | B39: P3 | C39: Srikanth | D39: Build | E39: Add typed settings (app/config.py) | F39: Create app/config.py from the Code sheet. Read every field and its comment. Note the validator that converts postgres:// and postgresql:// to postgresql+psycopg:// (Render gives the former). Copy services/backend/.env.example to .env (never commit .env). | G39: → Code: services/backend/app/config.py → Code: services/backend/.env.example cp .env.example .env | H39: BEFORE YOU START git pull --rebase SAVE YOUR WORK git add -A git status # nothing listed? then there is nothing to commit for this step git commit -m "P3.02: Add typed settings" git push # rejected? git pull --rebase, then git push again | I39: C05, C04 | J39: L18 | K39: uv run python -c "from app.config import get_settings; print(get_settings().database_url)" prints the 5433 URL. | L39: 0.5 | M39: Not started
A40: P3.03 | B40: P3 | C40: Siva prasad | D40: Build | E40: Add the database engine and session (app/db.py) | F40: Create app/db.py. Understand: Base (all models inherit), engine (connection pool, pool_pre_ping), SessionLocal, and get_db (one session per request, always closed). | G40: → Code: services/backend/app/db.py | H40: BEFORE YOU START git pull --rebase SAVE YOUR WORK git add -A git status # nothing listed? then there is nothing to commit for this step git commit -m "P3.03: Add the database engine and session" git push # rejected? git pull --rebase, then git push again | I40: C06 | J40: L16 | K40: File created; you can explain flush vs commit. | L40: 0.5 | M40: Not started
A41: P3.04 | B41: P3 | C41: Srikanth | D41: Learn | E41: Learn SQLAlchemy 2.0 | F41: Study lesson L16 and the 'ORM Quick Start' page. Pay attention to Mapped[...] annotations and session.commit(). | J41: L16 | K41: You can write a select() with a where() and run it with db.scalars(). | L41: 4 | M41: Not started
A42: P3.05 | B42: P3 | C42: Srikanth | D42: Build | E42: Define all database models (app/models.py) | F42: Create app/models.py from the Code sheet. Read each table and map it to the product: visitors (guests), games, import_runs, jobs (queue), analysis_runs, tactical_evidence, puzzles, practice_sessions, practice_events, concept_ratings. Note the database-level protections: UNIQUE(owner_id, source, source_game_id), UNIQUE(game_id, pipeline_version), unique dedupe_key, ON DELETE CASCADE from visitors. (Defining everything now means one initial migration; later phases use these tables.) | G42: → Code: services/backend/app/models.py | H42: BEFORE YOU START git pull --rebase SAVE YOUR WORK git add -A git status # nothing listed? then there is nothing to commit for this step git commit -m "P3.05: Define all database models" git push # rejected? git pull --rebase, then git push again | I42: C07 | J42: L14, L16 | K42: uv run python -c "import app.models" runs without errors. | L42: 1.5 | M42: Not started
A43: P3.06 | B43: P3 | C43: Siva prasad | D43: Build | E43: Set up Alembic and create the initial migration | F43: 1. Initialise Alembic in services/backend. 2. Make the 3 edits to migrations/env.py shown in the Code sheet (import models, use DATABASE_URL, target_metadata = Base.metadata). 3. Autogenerate the first migration and READ the generated file in migrations/versions/. 4. Apply it, then confirm models and migrations agree. 5. Look at the tables in psql (\dt). Verified result while preparing this plan: 10 tables + alembic_version, and 'No new upgrade operations detected'. | G43: → Code: services/backend/migrations/env.py.additions cd services/backend uv run alembic init migrations # edit migrations/env.py (Code: env.py.additions) uv run alembic revision --autogenerate -m "initial schema" uv run alembic upgrade head uv run alembic check docker compose exec db psql -U chesslab -d chesslab -c "\dt" | H43: BEFORE YOU START git pull --rebase SAVE YOUR WORK git add -A git status # nothing listed? then there is nothing to commit for this step git commit -m "P3.06: Set up Alembic and create the initial migration" git push # rejected? git pull --rebase, then git push again | I43: C08 | J43: L17 | K43: \dt lists 11 relations; alembic check passes. | L43: 1 | M43: Not started
A44: P3.07 | B44: P3 | C44: Srikanth | D44: Build | E44: Add the error contract (app/errors.py) | F44: Create app/errors.py: ApiError plus handlers for ApiError, request validation errors and unexpected exceptions. Every error becomes {"error": {"code", "message"}}; tracebacks go to logs only. | G44: → Code: services/backend/app/errors.py | H44: BEFORE YOU START git pull --rebase SAVE YOUR WORK git add -A git status # nothing listed? then there is nothing to commit for this step git commit -m "P3.07: Add the error contract" git push # rejected? git pull --rebase, then git push again | I44: C09 | J44: L22 | K44: File created; you can list three error codes the API will use. | L44: 0.5 | M44: Not started
A45: P3.08 | B45: P3 | C45: Siva prasad | D45: Build | E45: Add guest authentication (app/security.py) | F45: Study lesson L19 first. Create app/security.py: new_token (256-bit random), hash_token (sha256), expiry_from, and the current_visitor dependency (401 if missing, unknown or expired; sliding expiry). | G45: → Code: services/backend/app/security.py | H45: BEFORE YOU START git pull --rebase SAVE YOUR WORK git add -A git status # nothing listed? then there is nothing to commit for this step git commit -m "P3.08: Add guest authentication" git push # rejected? git pull --rebase, then git push again | I45: C10 | J45: L19 | K45: You can explain why the database never stores the raw token. | L45: 1 | M45: Not started
A46: P3.09 | B46: P3 | C46: Srikanth | D46: Build | E46: Add a simple rate limiter (app/ratelimit.py) | F46: Create app/ratelimit.py: an in-memory sliding window per client IP, used as a dependency: Depends(limit('sessions', 10, 60)). Read the docstring: fine for one API instance; move to Postgres/Redis if you ever scale out. | G46: → Code: services/backend/app/ratelimit.py | H46: BEFORE YOU START git pull --rebase SAVE YOUR WORK git add -A git status # nothing listed? then there is nothing to commit for this step git commit -m "P3.09: Add a simple rate limiter" git push # rejected? git pull --rebase, then git push again | I46: C11 | J46: L50 | K46: File created. | L46: 0.25 | M46: Not started
A47: P3.10 | B47: P3 | C47: Siva prasad | D47: Build | E47: Add the sessions router (app/api/sessions.py) | F47: Create app/api/sessions.py: POST /v1/sessions (rate-limited) returns the token ONCE; GET /v1/me returns the visitor id and expiry. | G47: → Code: services/backend/app/api/sessions.py | H47: BEFORE YOU START git pull --rebase SAVE YOUR WORK git add -A git status # nothing listed? then there is nothing to commit for this step git commit -m "P3.10: Add the sessions router" git push # rejected? git pull --rebase, then git push again | I47: C12 | J47: L12, L13 | K47: File created. | L47: 0.5 | M47: Not started
A48: P3.11 | B48: P3 | C48: Srikanth | D48: Build | E48: Create the app entry point (app/main.py) with stub routers | F48: Create app/main.py from the Code sheet. It imports 8 routers; until you build them, either create each module with a minimal 'router = APIRouter()' or temporarily include only sessions. Run the API and open the interactive docs. | G48: → Code: services/backend/app/main.py uv run uvicorn app.main:app --reload --port 8010 # open http://localhost:8010/docs | H48: BEFORE YOU START git pull --rebase SAVE YOUR WORK git add -A git status # nothing listed? then there is nothing to commit for this step git commit -m "P3.11: Create the app entry point with stub routers" git push # rejected? git pull --rebase, then git push again | I48: C13 | J48: L13, L21 | K48: http://localhost:8010/health/ready returns {"status":"ready"} and /docs lists POST /v1/sessions. | L48: 0.75 | M48: Not started
A49: P3.12 | B49: P3 | C49: Siva prasad | D49: Test | E49: Try the API by hand | F49: In /docs: call POST /v1/sessions, copy the token, click 'Authorize' and paste it, then call GET /v1/me. Then call GET /v1/me without authorising and see the 401 error shape. Look at the visitors table in psql: only a hash is stored. | G49: docker compose exec db psql -U chesslab -d chesslab -c "SELECT id, token_hash, expires_at FROM visitors;" | H49: BEFORE YOU START git pull --rebase SAVE YOUR WORK git add -A git status # nothing listed? then there is nothing to commit for this step git commit -m "P3.12: Try the API by hand" git push # rejected? git pull --rebase, then git push again | J49: L19, L22 | K49: You saw 201, 200 and 401 responses and a 64-character hash in the database. | L49: 0.5 | M49: Not started
A50: P3.13 | B50: P3 | C50: Srikanth | D50: Learn | E50: Learn pytest | F50: Study lesson L23 and the pytest 'Get Started' page. | J50: L23 | K50: You know what a fixture is. | L50: 1.5 | M50: Not started
A51: P3.14 | B51: P3 | C51: Siva prasad | D51: Test | E51: Add test fixtures (tests/conftest.py) | F51: Create tests/conftest.py from the Code sheet. It creates a separate chesslab_test database, builds the schema with create_all (fine for tests), truncates tables after every test, and provides client, auth and fork_puzzle fixtures. | G51: → Code: services/backend/tests/conftest.py | H51: BEFORE YOU START git pull --rebase SAVE YOUR WORK git add -A git status # nothing listed? then there is nothing to commit for this step git commit -m "P3.14: Add test fixtures" git push # rejected? git pull --rebase, then git push again | I51: C14 | J51: L23 | K51: File created. | L51: 0.5 | M51: Not started
A52: P3.15 | B52: P3 | C52: Srikanth | D52: Test | E52: Write and run the first API tests | F52: Create tests/test_api.py with test_health, test_private_routes_need_a_token (copy them from the Code sheet's test_api.py; the remaining tests in that file will pass as you complete later phases). Run pytest with the database running. | G52: → Code: services/backend/tests/test_api.py (first two tests) uv run pytest -q | H52: BEFORE YOU START git pull --rebase SAVE YOUR WORK git add -A git status # nothing listed? then there is nothing to commit for this step git commit -m "P3.15: Write and run the first API tests" git push # rejected? git pull --rebase, then git push again | I52: C73 | J52: L23 | K52: 2 passed. | L52: 0.5 | M52: Not started
A53: P3.16 | B53: P3 | C53: Siva prasad | D53: Test | E53: Lint and commit | F53: Run ruff (lint + import sorting) and fix anything it reports, then commit. | G53: uv run ruff check . --fix uv run pytest -q | H53: BEFORE YOU START git pull --rebase SAVE YOUR WORK git add -A git status # nothing listed? then there is nothing to commit for this step git commit -m "P3.16: Lint and commit" git push # rejected? git pull --rebase, then git push again | J53: L03 | K53: ruff reports 'All checks passed!'. | L53: 0.25 | M53: Not started
E54: P4 Playable game in the browser (Core) | F54: Board, rules, Stockfish WASM opponent, your original engine, promotion, PGN export.
A55: P4.01 | B55: P4 | C55: Siva prasad | D55: Learn | E55: Learn TypeScript and React fundamentals | F55: Study lessons L05 and L06. Do react.dev 'Quick Start' and 'Thinking in React'. Build the tic-tac-toe tutorial in a scratch folder. | J55: L05, L06 | K55: You can explain state vs props vs refs and what useEffect cleanup does. | L55: 10 | M55: Not started
A56: P4.02 | B56: P4 | C56: Srikanth | D56: Learn | E56: Learn chess notation and engines | F56: Study lessons L09 and L10. Paste a FEN into lichess.org/editor and a PGN into lichess.org/paste to see them on a board. | J56: L09, L10 | K56: You can convert a UCI move to SAN with a board and explain why FEN alone loses history. | L56: 2 | M56: Not started
A57: P4.03 | B57: P4 | C57: Srikanth | D57: Build | E57: Set up the app shell: main.tsx, index.css, App.tsx | F57: 1. Replace src/main.tsx and src/index.css with the Code sheet versions; delete src/App.css and src/assets. 2. Create src/App.tsx from the Code sheet. It imports pages you have not written yet: create each page file now with a placeholder component (export function PlayPage() { return <p>Play</p>; }) and replace them as you go. 3. Run npm run dev and click through the nav links; reload a deep link such as /methodology. | G57: → Code: apps/web/src/main.tsx → Code: apps/web/src/index.css → Code: apps/web/src/App.tsx | H57: BEFORE YOU START git pull --rebase SAVE YOUR WORK git add -A git status # nothing listed? then there is nothing to commit for this step git commit -m "P4.03: Set up the app shell: main.tsx, index.css, App.tsx" git push # rejected? git pull --rebase, then git push again | I57: C17, C18, C19 | J57: L06, L07 | K57: All nav links render placeholder pages; deep links work in dev. | L57: 1 | M57: Not started
A58: P4.04 | B58: P4 | C58: Siva prasad | D58: Build | E58: Add the API client and types | F58: Create src/api/client.ts (base URL, lazy guest session, Authorization header, ApiError, one retry on 401) and src/api/types.ts. Create apps/web/.env.local with VITE_API_BASE_URL=http://localhost:8010. | G58: → Code: apps/web/src/api/client.ts → Code: apps/web/src/api/types.ts → Code: apps/web/.env.example (copy to .env.local) | H58: BEFORE YOU START git pull --rebase SAVE YOUR WORK git add -A git status # nothing listed? then there is nothing to commit for this step git commit -m "P4.04: Add the API client and types" git push # rejected? git pull --rebase, then git push again | I58: C20, C21, C15 | J58: L05, L19 | K58: Files compile (npx tsc -b). | L58: 0.75 | M58: Not started
A59: P4.05 | B59: P4 | C59: Srikanth | D59: Test | E59: Write chess helper functions with unit tests | F59: Create src/game/chessHelpers.ts (isPromotion, uciOf, parseUci, statusOf, buildPgn, positionsFromPgn) and its test file. Add a test script to package.json: "test": "vitest run". Run the tests. | G59: → Code: apps/web/src/game/chessHelpers.ts → Code: apps/web/src/game/chessHelpers.test.ts npm test | H59: BEFORE YOU START git pull --rebase SAVE YOUR WORK git add -A git status # nothing listed? then there is nothing to commit for this step git commit -m "P4.05: Write chess helper functions with unit tests" git push # rejected? git pull --rebase, then git push again | I59: C22, C23 | J59: L24, L09 | K59: 4 tests pass (verified). | L59: 1 | M59: Not started
A60: P4.06 | B60: P4 | C60: Srikanth | D60: Learn | E60: Learn Web Workers | F60: Study lesson L08. Read the stockfish.js README section on using it in a browser worker. | J60: L08 | K60: You can explain postMessage/onmessage and why the engine must not run on the main thread. | L60: 1 | M60: Not started
A61: P4.07 | B61: P4 | C61: Siva prasad | D61: Setup | E61: Copy the Stockfish WASM build into public/ | F61: 1. List the files shipped by the npm package. 2. Copy the 'lite-single' JavaScript AND its .wasm file (same base name) into apps/web/public/stockfish/. Verified file names for stockfish 19.0.1: stockfish-19-lite-single.js and stockfish-19-lite-single.wasm (yours may differ by version). 3. Copy the package's licence file too (Copying.txt) to public/stockfish/ (GPLv3 requires it). | G61: ls node_modules/stockfish/bin mkdir -p public/stockfish cp node_modules/stockfish/bin/stockfish-*-lite-single.* public/stockfish/ cp node_modules/stockfish/Copying.txt public/stockfish/ | H61: BEFORE YOU START git pull --rebase SAVE YOUR WORK git add -A git status # nothing listed? then there is nothing to commit for this step git commit -m "P4.07: Copy the Stockfish WASM build into public/" git push # rejected? git pull --rebase, then git push again | J61: L08, L55 | K61: http://localhost:5180/stockfish/<name>.js loads in the browser (shows JavaScript). | L61: 0.25 | M61: Not started
A62: P4.08 | B62: P4 | C62: Srikanth | D62: Build | E62: Write the Stockfish worker wrapper | F62: Create src/engine/stockfish.ts. EDIT STOCKFISH_URL to the exact file you copied (e.g. /stockfish/stockfish-19-lite-single.js). Understand waitFor(): it sends a UCI command and resolves on the first output line with the expected prefix, with a timeout. bestMove() sends the start FEN plus the full move list (so repetitions are known). | G62: → Code: apps/web/src/engine/stockfish.ts | H62: BEFORE YOU START git pull --rebase SAVE YOUR WORK git add -A git status # nothing listed? then there is nothing to commit for this step git commit -m "P4.08: Write the Stockfish worker wrapper" git push # rejected? git pull --rebase, then git push again | I62: C24 | J62: L08, L10 | K62: Compiles; you can list the UCI commands it sends. | L62: 1 | M62: Not started
A63: P4.09 | B63: P4 | C63: Siva prasad | D63: Build | E63: Extract your original engine into a worker (no code changes to the engine) | F63: 1. Copy the old chess.js and lines 35-309 of js/main.js (weights, piece-square tables, evaluateBoard, minimax) into public/legacy-engine/. 2. Create public/legacy-engine/legacy-worker.js (Code sheet) and src/engine/legacy.ts. 3. Note the documented limitation: from a mid-game FEN the running evaluation sum restarts at 0. | G63: mkdir -p public/legacy-engine cp ../../js/chess.js public/legacy-engine/chess-legacy.js sed -n '35,309p' ../../js/main.js > public/legacy-engine/legacy-engine.js head -1 public/legacy-engine/legacy-engine.js && tail -1 public/legacy-engine/legacy-engine.js → Code: apps/web/public/legacy-engine/legacy-worker.js → Code: apps/web/src/engine/legacy.ts | H63: BEFORE YOU START git pull --rebase SAVE YOUR WORK git add -A git status # nothing listed? then there is nothing to commit for this step git commit -m "P4.09: Extract your original engine into a worker" git push # rejected? git pull --rebase, then git push again | I63: C25, C26 | J63: L08, L10 | K63: legacy-engine.js starts with 'var weights' and ends with the closing brace of minimax. | L63: 0.75 | M63: Not started
A64: P4.10 | B64: P4 | C64: Srikanth | D64: Build | E64: Build the game hook (useChessGame) | F64: Create src/game/useChessGame.ts. Study how it separates the mutable chess.js object (in a ref) from render state (view), how the engine effect asks for a move whenever it is the engine's turn (including the first move when you choose Black), and how gameIdRef discards late replies after restart or resign. | G64: → Code: apps/web/src/game/useChessGame.ts | H64: BEFORE YOU START git pull --rebase SAVE YOUR WORK git add -A git status # nothing listed? then there is nothing to commit for this step git commit -m "P4.10: Build the game hook" git push # rejected? git pull --rebase, then git push again | I64: C27 | J64: L06, L08 | K64: Compiles; you can explain the stale-reply guard. | L64: 2 | M64: Not started
A65: P4.11 | B65: P4 | C65: Siva prasad | D65: Build | E65: Build MoveList and PromotionDialog components | F65: Create src/components/MoveList.tsx (accessible table of moves, current/flagged highlighting) and src/components/PromotionDialog.tsx (all four promotion pieces, keyboard focus on Queen, cancel). | G65: → Code: apps/web/src/components/MoveList.tsx → Code: apps/web/src/components/PromotionDialog.tsx | H65: BEFORE YOU START git pull --rebase SAVE YOUR WORK git add -A git status # nothing listed? then there is nothing to commit for this step git commit -m "P4.11: Build MoveList and PromotionDialog components" git push # rejected? git pull --rebase, then git push again | I65: C28, C29 | J65: L54 | K65: Components render in the Play page later. | L65: 0.75 | M65: Not started
A66: P4.12 | B66: P4 | C66: Srikanth | D66: Build | E66: Build the Play page | F66: Create src/pages/PlayPage.tsx: side and opponent selection, the board (drag and click-to-move), last-move highlight, status line (aria-live), engine error with retry, resign, restart, new setup, PGN export, and 'Review game' after the game ends. react-chessboard v4 props used: position, boardOrientation, onPieceDrop, onSquareClick, onPromotionCheck (returns false so OUR dialog handles promotion), customSquareStyles, arePiecesDraggable. | G66: → Code: apps/web/src/pages/PlayPage.tsx | H66: BEFORE YOU START git pull --rebase SAVE YOUR WORK git add -A git status # nothing listed? then there is nothing to commit for this step git commit -m "P4.12: Build the Play page" git push # rejected? git pull --rebase, then git push again | I66: C30 | J66: L06, L54 | K66: You can play a full game against Stockfish in the browser at http://localhost:5180/play. | L66: 4 | M66: Not started
A67: P4.13 | B67: P4 | C67: Srikanth | D67: Test | E67: Manually test the rules edge cases | F67: Use the board to check: castling both sides; castling is refused through check; en passant; all four promotions (set up quickly by playing, or temporarily start from a FEN); checkmate message; stalemate; threefold repetition; resign during engine thinking; restart during engine thinking (no stray engine move appears); choosing Black (engine moves first). Write results in docs/acceptance.md. | H67: BEFORE YOU START git pull --rebase SAVE YOUR WORK git add -A git status # nothing listed? then there is nothing to commit for this step git commit -m "P4.13: Manually test the rules edge cases" git push # rejected? git pull --rebase, then git push again | J67: L09 | K67: Every edge case behaves correctly or has a written issue. | L67: 1.5 | M67: Not started
A68: P4.14 | B68: P4 | C68: Siva prasad | D68: Test | E68: Add Playwright end-to-end tests for play | F68: Create playwright.config.ts and e2e/play.spec.ts (Code sheet). They verify: Stockfish replies as White when you choose Black; the original engine replies; deep links load. Add a script "e2e": "playwright test". Verified result while preparing this plan: 3 passed in Chromium. | G68: → Code: apps/web/playwright.config.ts → Code: apps/web/e2e/play.spec.ts npx playwright test e2e/play.spec.ts | H68: BEFORE YOU START git pull --rebase SAVE YOUR WORK git add -A git status # nothing listed? then there is nothing to commit for this step git commit -m "P4.14: Add Playwright end-to-end tests for play" git push # rejected? git pull --rebase, then git push again | I68: C31, C32 | J68: L24 | K68: 3 passed. | L68: 1 | M68: Not started
A69: P4.15 | B69: P4 | C69: Siva prasad | D69: Test | E69: Type-check, build, lint and commit | F69: Run the same checks CI will run. Fix all TypeScript errors. The Vite template's linter (oxlint) may warn about React rules; aim for zero warnings. | G69: npx tsc -b npm run build npm run lint | H69: BEFORE YOU START git pull --rebase SAVE YOUR WORK git add -A git status # nothing listed? then there is nothing to commit for this step git commit -m "P4.15: Type-check, build, lint and commit" git push # rejected? git pull --rebase, then git push again | J69: L07 | K69: Build succeeds; dist/ is created (not committed). | L69: 0.25 | M69: Not started
E70: P5 First public deployment (thin slice) (Core) | F70: Render (API + Postgres) and Vercel (frontend) live; CORS and env vars proven; CI. ► Checkpoint A: a stranger can play a complete game on the public URL
A71: P5.01 | B71: P5 | C71: Siva prasad | D71: Learn | E71: Learn deployment on Render and Vercel | F71: Study lesson L48 and read Render's 'Web services', 'Background workers' and 'Free instance limitations' pages. | J71: L48 | K71: You can explain why the worker can't be serverless and why free plans sleep. | L71: 2 | M71: Not started
A72: P5.02 | B72: P5 | C72: Srikanth | D72: Build | E72: Write the backend Dockerfile and build it locally | F72: 1. Create services/backend/Dockerfile and .dockerignore (Code sheet). 2. Export pinned requirements from uv.lock (the image uses pip). 3. Build and run the image; check Stockfish inside it. Verified: the image builds and contains Stockfish 15.1 at /usr/games/stockfish. | G72: → Code: services/backend/.dockerignore → Code: services/backend/Dockerfile cd services/backend uv export --frozen --no-dev --no-emit-project --no-hashes -o requirements.txt docker build -t chesslab-backend . MSYS_NO_PATHCONV=1 docker run --rm chesslab-backend sh -c "echo uci | /usr/games/stockfish | head -1" | H72: BEFORE YOU START git pull --rebase SAVE YOUR WORK git add -A git status # nothing listed? then there is nothing to commit for this step git commit -m "P5.02: Write the backend Dockerfile and build it locally" git push # rejected? git pull --rebase, then git push again | I72: C34, C33 | J72: L25 | K72: The last command prints 'Stockfish 15.1 by the Stockfish developers...' (or your version). | L72: 1 | M72: Not started
A73: P5.03 | B73: P5 | C73: Siva prasad | D73: Test | E73: Run the whole backend stack with Compose | F73: Start db + api (+ worker later) with Compose. The api command runs migrations first. Check health from your machine on port 8010. | G73: docker compose up --build -d docker compose ps curl http://localhost:8010/health/ready docker compose logs api --tail 20 | H73: BEFORE YOU START git pull --rebase SAVE YOUR WORK git add -A git status # nothing listed? then there is nothing to commit for this step git commit -m "P5.03: Run the whole backend stack with Compose" git push # rejected? git pull --rebase, then git push again | J73: L26 | K73: health/ready returns ready from the container. | L73: 0.5 | M73: Not started
A74: P5.04 | B74: P5 | C74: Srikanth | D74: Deploy | E74: Check that main has all the P2-P4 work | F74: Pull the latest main and make sure it builds from a clean install on your laptop. | G74: git pull --rebase git log --oneline -15 cd apps/web && npm ci && npm run build | H74: BEFORE YOU START git pull --rebase SAVE YOUR WORK git add -A git status # nothing listed? then there is nothing to commit for this step git commit -m "P5.04: Check that main has all the P2-P4 work" git push # rejected? git pull --rebase, then git push again | J74: L03 | K74: main builds from a fresh install. | L74: 0.25 | M74: Not started
A75: P5.05 | B75: P5 | C75: Siva prasad | D75: Deploy | E75: Add CI with GitHub Actions | F75: Create .github/workflows/ci.yml (Code sheet). It runs backend lint, migrations (upgrade + check), pytest against a Postgres service container and a docker build; and frontend npm ci, lint, tsc, vitest, build and the Playwright play tests. Push and watch the Actions tab until both jobs are green. CI now runs on every push to main; keep it green. | G75: → Code: .github/workflows/ci.yml | H75: BEFORE YOU START git pull --rebase SAVE YOUR WORK git add -A git status # nothing listed? then there is nothing to commit for this step git commit -m "P5.05: Add CI with GitHub Actions" git push # rejected? git pull --rebase, then git push again | I75: C37 | J75: L49 | K75: Both CI jobs pass; main requires CI. | L75: 1.5 | M75: Not started
A76: P5.06 | B76: P5 | C76: Srikanth | D76: Deploy | E76: Create the Render Postgres database | F76: Render dashboard > New > Postgres. Name chesslab-db, choose a region near you (e.g. Singapore or Frankfurt) and keep API/worker in the SAME region. Choose a paid plan if you want it to persist (free databases expire). Copy the Internal Database URL (you will reference it, not paste it in code). | H76: BEFORE YOU START git pull --rebase SAVE YOUR WORK git add -A git status # nothing listed? then there is nothing to commit for this step git commit -m "P5.06: Create the Render Postgres database" git push # rejected? git pull --rebase, then git push again | J76: L48 | K76: chesslab-db shows 'Available'. | L76: 0.5 | M76: Not started
A77: P5.07 | B77: P5 | C77: Srikanth | D77: Deploy | E77: Create the Render web service for the API | F77: Option A (recommended): New > Blueprint, select your repo; render.yaml (Code sheet) creates db, api and worker together. Option B: New > Web Service > Docker, root directory services/backend. Set env vars: DATABASE_URL (from database), ENVIRONMENT=production, ALLOWED_ORIGINS (temporary: http://localhost:5180), health check path /health/ready, pre-deploy command 'alembic upgrade head'. Deploy and open https://<name>.onrender.com/health/ready. | G77: → Code: render.yaml | H77: BEFORE YOU START git pull --rebase SAVE YOUR WORK git add -A git status # nothing listed? then there is nothing to commit for this step git commit -m "P5.07: Create the Render web service for the API" git push # rejected? git pull --rebase, then git push again | I77: C35 | J77: L48, L17 | K77: The public /health/ready returns ready; /docs loads over HTTPS. | L77: 1 | M77: Not started
A78: P5.08 | B78: P5 | C78: Srikanth | D78: Deploy | E78: Deploy the frontend to Vercel | F78: 1. Add apps/web/vercel.json (Code sheet) with the SPA rewrite and security headers; replace YOUR-API in the CSP connect-src with your Render API host. 2. Vercel > Add New Project > import the repo > Root Directory: apps/web; Framework: Vite; Build: npm run build; Output: dist. 3. Environment variable VITE_API_BASE_URL = https://<your-api>.onrender.com (no trailing slash). Deploy. | G78: → Code: apps/web/vercel.json | H78: BEFORE YOU START git pull --rebase SAVE YOUR WORK git add -A git status # nothing listed? then there is nothing to commit for this step git commit -m "P5.08: Deploy the frontend to Vercel" git push # rejected? git pull --rebase, then git push again | I78: C36 | J78: L07, L48, L50 | K78: https://<project>.vercel.app/play loads and you can play a game. | L78: 0.75 | M78: Not started
A79: P5.09 | B79: P5 | C79: Srikanth | D79: Deploy | E79: Connect frontend and backend (CORS) | F79: Set ALLOWED_ORIGINS on the Render API to your exact Vercel origin (https://<project>.vercel.app, no trailing slash) and redeploy. Open the Vercel site, open DevTools > Console and run: fetch('https://<your-api>.onrender.com/v1/sessions', {method: 'POST'}).then(r => r.json()).then(console.log). Then open DevTools > Network and look at the preflight OPTIONS request and its Access-Control-Allow-Origin response header. | H79: BEFORE YOU START git pull --rebase SAVE YOUR WORK git add -A git status # nothing listed? then there is nothing to commit for this step git commit -m "P5.09: Connect frontend and backend" git push # rejected? git pull --rebase, then git push again | J79: L21 | K79: The browser console shows a token; no CORS error. A request from another origin is blocked. | L79: 0.5 | M79: Not started
A80: P5.10 | B80: P5 | C80: Siva prasad | D80: Test | E80: Verify the thin slice from a fresh browser | F80: Use an incognito window on your phone (mobile data, not your Wi-Fi) and: open the site; choose Black; receive an engine move; play a few moves; reload a deep link (/methodology). Then restart the Render API service and confirm sessions still work (state is in Postgres). | H80: BEFORE YOU START git pull --rebase SAVE YOUR WORK git add -A git status # nothing listed? then there is nothing to commit for this step git commit -m "P5.10: Verify the thin slice from a fresh browser" git push # rejected? git pull --rebase, then git push again | J80: L48 | K80: Checkpoint A reached: a stranger can play a complete game on the public URL. | L80: 0.5 | M80: Not started
A81: P5.11 | B81: P5 | C81: Srikanth | D81: Doc | E81: Record the deployment | F81: Start docs/OPERATIONS.md from the template: service names, URLs, region, plans, env var NAMES (never values). Tag the release. | G81: → Code: docs/OPERATIONS_TEMPLATE.md git tag checkpoint-a && git push --tags | H81: BEFORE YOU START git pull --rebase SAVE YOUR WORK git add -A git status # nothing listed? then there is nothing to commit for this step git commit -m "P5.11: Record the deployment" git push # rejected? git pull --rebase, then git push again | I81: C84 | J81: L49 | K81: OPERATIONS.md committed; tag pushed. | L81: 0.5 | M81: Not started
E82: P6 Saving games and the durable job queue (Core) | F82: Server re-validates games; Postgres queue with leases; the worker process with Stockfish.
A83: P6.01 | B83: P6 | C83: Srikanth | D83: Learn | E83: Learn background jobs and Postgres queues | F83: Study lessons L27, L28 and L29. Draw the job state diagram (queued -> running -> succeeded / retry_wait / failed / cancelled) on paper. | J83: L27, L28, L29 | K83: You can explain SKIP LOCKED, leases and fencing tokens. | L83: 5 | M83: Not started
A84: P6.02 | B84: P6 | C84: Siva prasad | D84: Build | E84: Add PGN parsing and validation (app/domain/pgn.py) | F84: Create app/domain/pgn.py: parse_single, iter_games (per-game errors), player_color_for, a fingerprint for games without provider ids, and bounds (400 plies). Note that python-chess records illegal moves in game.errors instead of raising. | G84: → Code: services/backend/app/domain/pgn.py | H84: BEFORE YOU START git pull --rebase SAVE YOUR WORK git add -A git status # nothing listed? then there is nothing to commit for this step git commit -m "P6.02: Add PGN parsing and validation" git push # rejected? git pull --rebase, then git push again | I84: C38 | J84: L33, L34 | K84: File created. | L84: 1 | M84: Not started
A85: P6.03 | B85: P6 | C85: Srikanth | D85: Test | E85: Test the PGN parser | F85: Create tests/test_learning_and_pgn.py from the Code sheet (it also contains Elo and template tests you will need later; keep them, they will pass once those modules exist, or add them later). Run the PGN tests. | G85: → Code: services/backend/tests/test_learning_and_pgn.py uv run pytest -q -k pgn | H85: BEFORE YOU START git pull --rebase SAVE YOUR WORK git add -A git status # nothing listed? then there is nothing to commit for this step git commit -m "P6.03: Test the PGN parser" git push # rejected? git pull --rebase, then git push again | I85: C72 | J85: L23 | K85: PGN tests pass (good game, illegal move, variant, per-game errors). | L85: 0.5 | M85: Not started
A86: P6.04 | B86: P6 | C86: Siva prasad | D86: Build | E86: Build the job queue (app/jobs/queue.py) | F86: Create app/jobs/queue.py. Read CLAIM_SQL slowly: the inner SELECT finds the best ready job (or one whose lease expired), FOR UPDATE SKIP LOCKED takes it without waiting for other workers, the outer UPDATE marks it running with a 60 s lease and attempts+1. All later updates are fenced with 'AND attempts = :attempts AND status = running'. | G86: → Code: services/backend/app/jobs/queue.py | H86: BEFORE YOU START git pull --rebase SAVE YOUR WORK git add -A git status # nothing listed? then there is nothing to commit for this step git commit -m "P6.04: Build the job queue" git push # rejected? git pull --rebase, then git push again | I86: C39 | J86: L28, L29 | K86: File created; you can explain each line of CLAIM_SQL. | L86: 2 | M86: Not started
A87: P6.05 | B87: P6 | C87: Srikanth | D87: Build | E87: Add the games API (save played games) | F87: Create app/api/games.py: POST /v1/games re-validates the PGN, inserts with ON CONFLICT DO NOTHING (double clicks reuse the same game), enqueues analysis with dedupe_key and priority 10, and commits game + job together. GET list/detail use get_owned_game (404 for others). POST /{id}/analysis re-requests analysis. | G87: → Code: services/backend/app/api/games.py | H87: BEFORE YOU START git pull --rebase SAVE YOUR WORK git add -A git status # nothing listed? then there is nothing to commit for this step git commit -m "P6.05: Add the games API" git push # rejected? git pull --rebase, then git push again | I87: C40 | J87: L12, L20, L29 | K87: File created and router included in main.py. | L87: 1.5 | M87: Not started
A88: P6.06 | B88: P6 | C88: Siva prasad | D88: Build | E88: Add the jobs API (status and cancel) | F88: Create app/api/jobs.py: GET /v1/jobs/{id} (owner only; returns status, attempts, progress, safe error code) and POST /v1/jobs/{id}/cancel (queued jobs cancel immediately; running jobs stop at the next heartbeat). | G88: → Code: services/backend/app/api/jobs.py | H88: BEFORE YOU START git pull --rebase SAVE YOUR WORK git add -A git status # nothing listed? then there is nothing to commit for this step git commit -m "P6.06: Add the jobs API" git push # rejected? git pull --rebase, then git push again | I88: C41 | J88: L20, L27 | K88: File created. | L88: 0.5 | M88: Not started
A89: P6.07 | B89: P6 | C89: Srikanth | D89: Test | E89: Test idempotency, ownership and the queue | F89: Add these tests from tests/test_api.py: test_save_game_is_idempotent_and_queues_one_job, test_illegal_pgn_is_rejected, test_other_guests_cannot_read_my_game, test_two_workers_never_claim_the_same_job (4 threads, 30 jobs, no duplicates), test_stale_worker_cannot_overwrite, test_cancel_queued_job. | G89: uv run pytest -q tests/test_api.py | H89: BEFORE YOU START git pull --rebase SAVE YOUR WORK git add -A git status # nothing listed? then there is nothing to commit for this step git commit -m "P6.07: Test idempotency, ownership and the queue" git push # rejected? git pull --rebase, then git push again | J89: L23, L28 | K89: All queue and ownership tests pass (verified). | L89: 1 | M89: Not started
A90: P6.08 | B90: P6 | C90: Siva prasad | D90: Learn | E90: Learn python-chess and engine scores | F90: Study lessons L34 and L35. In a scratch script, open Stockfish via the Docker image and analyse the start position with Limit(depth=12). | G90: MSYS_NO_PATHCONV=1 docker run --rm chesslab-backend python -c "import chess, chess.engine; e=chess.engine.SimpleEngine.popen_uci('/usr/games/stockfish'); print(e.analyse(chess.Board(), chess.engine.Limit(depth=12))['score']); e.quit()" | J90: L34, L35 | K90: You saw a PovScore and can convert it to White's point of view. | L90: 2 | M90: Not started
A91: P6.09 | B91: P6 | C91: Srikanth | D91: Build | E91: Add the engine adapter (app/analysis/engine.py) | F91: Create app/analysis/engine.py: MoveEval, the Evaluator protocol (so tests can use a fake), and StockfishEvaluator (one long-lived process per worker, restarted on failure, configured threads/hash, analyse(..., root_moves=[move]) to score a SPECIFIC move from the mover's point of view). | G91: → Code: services/backend/app/analysis/engine.py | H91: BEFORE YOU START git pull --rebase SAVE YOUR WORK git add -A git status # nothing listed? then there is nothing to commit for this step git commit -m "P6.09: Add the engine adapter" git push # rejected? git pull --rebase, then git push again | I91: C42 | J91: L34, L35 | K91: File created. | L91: 1 | M91: Not started
A92: P6.10 | B92: P6 | C92: Siva prasad | D92: Build | E92: Add job handlers and the worker loop | F92: Create app/jobs/handlers.py (analyze_game now; import_lichess is used in P7) and app/worker.py (claim -> run -> complete/fail/cancel, SIGTERM-safe, sweeps exhausted leases every minute). analyze_game depends on the analysis pipeline from P8: create app/analysis/pipeline.py now as a stub returning AnalysisResult() with no findings, or build P8 first and return here. | G92: → Code: services/backend/app/jobs/handlers.py → Code: services/backend/app/worker.py | H92: BEFORE YOU START git pull --rebase SAVE YOUR WORK git add -A git status # nothing listed? then there is nothing to commit for this step git commit -m "P6.10: Add job handlers and the worker loop" git push # rejected? git pull --rebase, then git push again | I92: C43, C44 | J92: L27, L29, L52 | K92: uv run python -m app.worker starts and logs 'worker started'. | L92: 2.5 | M92: Not started
A93: P6.11 | B93: P6 | C93: Siva prasad | D93: Test | E93: Run the worker in Compose and watch a job | F93: Start the worker service, save a game through the API (/docs or the Play page's 'Review game'), and watch the worker log line: job=1 kind=analyze_game attempt=1 outcome=succeeded duration_ms=... | G93: docker compose up --build -d docker compose logs -f worker | H93: BEFORE YOU START git pull --rebase SAVE YOUR WORK git add -A git status # nothing listed? then there is nothing to commit for this step git commit -m "P6.11: Run the worker in Compose and watch a job" git push # rejected? git pull --rebase, then git push again | J93: L26, L52 | K93: A job moves from queued to succeeded; jobs table shows status succeeded. | L93: 0.5 | M93: Not started
A94: P6.12 | B94: P6 | C94: Srikanth | D94: Test | E94: Prove crash recovery | F94: Make a job slow (temporarily set ANALYSIS_TIME_S=3 for the worker), save a long game, and while it runs: docker compose kill worker. Wait for the 60 s lease to expire, start the worker again, and see the same job reclaimed with attempt=2 and succeed. | G94: docker compose kill worker docker compose up -d worker docker compose logs -f worker | H94: BEFORE YOU START git pull --rebase SAVE YOUR WORK git add -A git status # nothing listed? then there is nothing to commit for this step git commit -m "P6.12: Prove crash recovery" git push # rejected? git pull --rebase, then git push again | J94: L28 | K94: The killed job finishes on attempt 2; no duplicate evidence rows. | L94: 0.75 | M94: Not started
A95: P6.13 | B95: P6 | C95: Siva prasad | D95: Deploy | E95: Wire 'Review game' in the UI and commit | F95: The Play page already POSTs /v1/games and shows 'Open review'. Play a short game locally, resign, click Review game, and confirm a job is created. Push; let CI pass; Render redeploys api; create the Render background worker (render.yaml includes it). | H95: BEFORE YOU START git pull --rebase SAVE YOUR WORK git add -A git status # nothing listed? then there is nothing to commit for this step git commit -m "P6.13: Wire 'Review game' in the UI and commit" git push # rejected? git pull --rebase, then git push again | J95: L49 | K95: On the live site, a finished game creates a job that the Render worker completes. | L95: 1 | M95: Not started
E96: P7 Importing history: Lichess and PGN upload (Core) | F96: Streaming provider import, dedupe, progress, cancellation, upload validation.
A97: P7.01 | B97: P7 | C97: Siva prasad | D97: Learn | E97: Learn to consume third-party APIs | F97: Study lesson L32 and read the Lichess 'Export games of a user' docs and the API tips page. | J97: L32 | K97: You know Lichess's 429 rule and what NDJSON is. | L97: 1 | M97: Not started
A98: P7.02 | B98: P7 | C98: Srikanth | D98: Build | E98: Write the Lichess importer | F98: Create app/importers/lichess.py: fetch_raw streams NDJSON with timeouts and a User-Agent and maps 404/429/5xx/timeouts to Permanent/Retryable errors; normalize() keeps standard, finished games with a PGN and works out the player's colour. Set PROVIDER_USER_AGENT to include your contact email. | G98: → Code: services/backend/app/importers/lichess.py | H98: BEFORE YOU START git pull --rebase SAVE YOUR WORK git add -A git status # nothing listed? then there is nothing to commit for this step git commit -m "P7.02: Write the Lichess importer" git push # rejected? git pull --rebase, then git push again | I98: C45 | J98: L32, L29 | K98: File created. | L98: 1 | M98: Not started
A99: P7.03 | B99: P7 | C99: Siva prasad | D99: Test | E99: Smoke-test the importer against live Lichess (manually, not in CI) | F99: Fetch 3 public games of a known player and a nonexistent user. Verified while preparing this plan: 3 standard blitz games parsed (91, 34, 36 plies) and the fake user raised USER_NOT_FOUND. | G99: uv run python -c "from app.importers import lichess; print([lichess.normalize(r, 'DrNykterstein').source_game_id for r in lichess.fetch_raw('DrNykterstein', 3, 'ChessLab dev test (you@example.com)')])" | H99: BEFORE YOU START git pull --rebase SAVE YOUR WORK git add -A git status # nothing listed? then there is nothing to commit for this step git commit -m "P7.03: Smoke-test the importer against live Lichess" git push # rejected? git pull --rebase, then git push again | J99: L32 | K99: Three game ids printed. | L99: 0.25 | M99: Not started
A100: P7.04 | B100: P7 | C100: Srikanth | D100: Test | E100: Save a provider fixture for tests | F100: Save one real NDJSON line to tests/fixtures/lichess_game.ndjson (trim it). Write a unit test for normalize() using it, so CI never calls Lichess. | H100: BEFORE YOU START git pull --rebase SAVE YOUR WORK git add -A git status # nothing listed? then there is nothing to commit for this step git commit -m "P7.04: Save a provider fixture for tests" git push # rejected? git pull --rebase, then git push again | J100: L23, L32 | K100: test passes offline. | L100: 0.5 | M100: Not started
...

Sheet Lessons
A1: ID | B1: Lesson | C1: Level | D1: Minutes | E1: Used in phases | F1: Status (edit) | G1: Open | H1: My notes (edit)
A2: L01 | B2: How the web works: browsers, servers, HTTP and JSON | C2: Beginner | D2: 60 | E2: P0, P3, P4 | F2: Not started | G2: Open →
A3: L02 | B3: The terminal on Windows: Git Bash, paths and environment variables | C3: Beginner | D3: 45 | E3: P0 and every phase | F3: Not started | G3: Open →
A4: L03 | B4: Git and GitHub: commits, branches, pull requests | C4: Beginner | D4: 75 | E4: P0, P1 and every phase | F4: Not started | G4: Open →
A5: L04 | B5: Package managers and lockfiles (npm for JavaScript, uv for Python) | C5: Beginner | D5: 40 | E5: P2, P3, P4 | F5: Not started | G5: Open →
A6: L05 | B6: TypeScript essentials for this project | C6: Beginner | D6: 90 | E6: P4, P9, P10 | F6: Not started | G6: Open →
A7: L06 | B7: React fundamentals: components, props, state, effects and refs | C7: Beginner | D7: 150 | E7: P4, P9, P10, P11 | F7: Not started | G7: Open →
A8: L07 | B8: Vite, dev servers and production builds | C8: Beginner | D8: 30 | E8: P2, P4, P5 | F8: Not started | G8: Open →
A9: L08 | B9: Web Workers: keeping the page responsive while an engine thinks | C9: Intermediate | D9: 40 | E9: P4 | F9: Not started | G9: Open →
A10: L09 | B10: Chess notation for programmers: FEN, PGN, SAN and UCI | C10: Beginner | D10: 45 | E10: P4, P6, P8, P10 | F10: Not started | G10: Open →
A11: L10 | B11: How chess engines work: minimax, alpha-beta, evaluation, and Stockfish over UCI | C11: Intermediate | D11: 90 | E11: P1, P4, P8, S4 | F11: Not started | G11: Open →
A12: L11 | B12: Python projects: virtual environments, packages, modules and imports (with uv) | C12: Beginner | D12: 60 | E12: P2, P3 | F12: Not started | G12: Open →
A13: L12 | B13: Designing a REST API and choosing status codes | C13: Beginner | D13: 45 | E13: P3, P6, P7, P10 | F13: Not started | G13: Open →
... A60: L59 | B60: Sharing one repository as two people: pull, commit, push and fixing conflicts | C60: Beginner | D60: 30 | E60: G0 and every chapter | F60: Not started | G60: Open →
B62: Total study time (hours) | D62: =SUM(D2:D60)/60
B63: Lessons marked Done | D63: =COUNTIF(F2:F60,"Done")

Sheet Lesson Notes
A1: Lesson notes. Each lesson: why it matters, the core concepts, how it is used in ChessLab, common mistakes, self-check questions and resources (click to open).
A3: L01 | B3: How the web works: browsers, servers, HTTP and JSON · Beginner · about 60 min · used in P0, P3, P4
B4: ↑ back to Lessons index
A5: Why it matters | B5: Everything in ChessLab is a conversation between a browser (the React app) and a server (the FastAPI app). If you understand what a request and a response are, every later lesson becomes 'just details'.
A6: Concept 1 | B6: Client and server: the browser is a client. It downloads HTML, CSS and JavaScript from a static host (Vercel), then runs that JavaScript. The JavaScript then talks to a different program, the API server (Render), which owns the database.
A7: Concept 2 | B7: An HTTP request has: a METHOD (GET = read, POST = create/act, DELETE = remove, PUT/PATCH = update), a URL path (/v1/games/123), HEADERS (metadata such as Authorization: Bearer <token>, Content-Type: application/json) and an optional BODY (usually JSON).
A8: Concept 3 | B8: An HTTP response has: a STATUS CODE (200 OK, 201 Created, 204 No Content, 400/422 bad input, 401 not logged in, 404 not found, 409 conflict, 429 too many requests, 500 server bug), headers and a body.
A9: Concept 4 | B9: JSON is plain text that looks like JavaScript objects: {"game_id": "abc", "moves": ["e2e4"]}. Both TypeScript and Python convert it to and from native objects.
A10: Concept 5 | B10: HTTPS = HTTP inside an encrypted TLS tunnel. Tokens and passwords must only ever travel over HTTPS. Vercel and Render give you HTTPS automatically.
A11: Concept 6 | B11: Statelessness: each HTTP request stands alone. The server remembers who you are only because the browser sends a token with every request; durable memory lives in the database, never in a Python variable.
A12: Concept 7 | B12: Origins: an origin is scheme + host + port (https://chesslab.vercel.app and https://chesslab-api.onrender.com are DIFFERENT origins). Browsers restrict JavaScript talking across origins; that is why CORS (lesson L21) exists.
A13: In ChessLab | B13: The React app calls fetch('https://<api>/v1/games', {method: 'POST', headers: {Authorization: 'Bearer ...'}, body: JSON.stringify({...})}). FastAPI receives it, validates the JSON, writes rows to Postgres, and returns 201 with JSON. You can watch every such request in the browser's DevTools > Network tab: make that a habit.
A14: Common mistake | B14: Thinking the frontend and backend are 'one program'. They are separate programs, deployed separately, talking over the network.
A15: Common mistake | B15: Putting secrets in frontend code. Anything shipped to the browser is public.
A16: Common mistake | B16: Ignoring status codes and only reading the body. The status code tells you what kind of failure happened.
... A25: L02 | B25: The terminal on Windows: Git Bash, paths and environment variables · Beginner · about 45 min · used in P0 and every phase
B26: ↑ back to Lessons index
A27: Why it matters | B27: You will run hundreds of commands, and every one in this manual is written for Git Bash. Most beginner frustration comes from the wrong folder, a stale PATH, or Git Bash's path conversion. This lesson removes all three.
A28: Concept 1 | B28: Git Bash comes with Git for Windows. It gives you a Unix-style shell (bash) on Windows, so the same commands work on Linux servers, in Docker containers and in GitHub Actions. git, npm, uv, docker and gh all run inside it.
A29: Concept 2 | B29: Paths: Git Bash writes drives as /d/my_learning/Chess-AI instead of D:\my_learning\Chess-AI. Your home folder is ~ (C:/Users/<you>). Windows programs called from Git Bash usually accept both styles. Quote paths that contain spaces.
A30: Concept 3 | B30: Working directory: commands run relative to your current folder. cd moves, pwd shows where you are, ls -la lists files. Most 'file not found' errors mean you are in the wrong folder.
A31: Concept 4 | B31: Environment variables: export NAME=value sets one for this session; echo $NAME prints it. A program only sees variables set BEFORE it started, so restart it after a change. Lines in ~/.bashrc run in every new Git Bash window and affect every project, so keep project settings out of it.
A32: Concept 5 | B32: PATH lists folders where the shell looks for programs. 'command not found' straight after installing something usually means: close and reopen Git Bash.
A33: Concept 6 | B33: Chaining: a && b runs b only if a succeeded; a || b runs b only if a failed; a | b sends a's output into b (grep, head, tail filter output). These replace PowerShell's ';', Select-String and Select-Object.
A34: Concept 7 | B34: Path conversion: when Git Bash calls a Windows program it rewrites arguments that look like Unix paths, so /usr/games/stockfish becomes C:/Program Files/Git/usr/games/stockfish. Paths INSIDE a Docker container must not be rewritten: prefix such docker commands with MSYS_NO_PATHCONV=1 (the manual does this for you). For volume mounts use "$(pwd -W)", which prints the Windows form of the current folder.
A35: Concept 8 | B35: Heredocs: cmd <<'EOF' ... EOF feeds several lines into a command or file (P2.07 uses one to send SQL to psql).
A36: Concept 9 | B36: Ports: a server listens on a port. Two programs cannot share one. On Srikanth's laptop 5432, 8000 and 5173 are already used by other projects, so ChessLab uses 5433, 8010 and 5180 on both laptops.
A37: In ChessLab | B37: Every command in this manual is written for Git Bash. Docker commands that contain container paths start with MSYS_NO_PATHCONV=1.
A38: Common mistake | B38: Running a command in the wrong folder (for example npm install in the repo root instead of apps/web).
... A50: L03 | B50: Git and GitHub: commits, branches, pull requests · Beginner · about 75 min · used in P0, P1 and every phase
B51: ↑ back to Lessons index
A52: Why it matters | B52: Git is your undo button, your history, and the way you deploy (Vercel and Render deploy from GitHub). Recruiters also read your commit history.
A53: Concept 1 | B53: A commit is a snapshot of the project with a message explaining WHY something changed. Commit small, coherent steps (one feature or fix each).
A54: Concept 2 | B54: The staging area: 'git add <file>' chooses what goes into the next commit; 'git commit -m "..."' records it. 'git status' and 'git diff' show what changed. Run them constantly.
A55: Concept 3 | B55: Branches let you try something risky without touching main (git switch -c experiment). In this project the two of you mostly work directly on main and push small commits.
A56: Concept 4 | B56: Remote: GitHub holds a copy (origin). 'git push' uploads commits; 'git pull' downloads. Vercel/Render watch a branch and redeploy on every push.
A57: Concept 5 | B57: Never commit secrets (.env), build output (dist/, node_modules/) or huge data files. .gitignore lists what Git should ignore. If you commit a secret, rotating (changing) the secret is mandatory; deleting the file is not enough because history keeps it.
A58: Concept 6 | B58: Tags mark releases (git tag v1.0.0) and give you a known-good revision to roll back to.
A59: Concept 7 | B59: Conventional commit messages (feat:, fix:, docs:, test:, chore:) make history readable.
A60: In ChessLab | B60: G0 connected this folder to GitHub and tagged the original app (original-app). Every step that changes files ends with pull, commit, push to main. Render and Vercel deploy main, so keep it working.
A61: Common mistake | B61: One giant commit called 'update'.
A62: Common mistake | B62: Working directly on main and breaking production.
A63: Common mistake | B63: Committing node_modules or .env.
... A72: L04 | B72: Package managers and lockfiles (npm for JavaScript, uv for Python) · Beginner · about 40 min · used in P2, P3, P4
B73: ↑ back to Lessons index
A74: Why it matters | B74: Your app depends on hundreds of libraries. Package managers download them; lockfiles guarantee that your laptop, CI and production all get exactly the same versions.
A75: Concept 1 | B75: package.json (JS) and pyproject.toml (Python) list your DIRECT dependencies with version ranges (e.g. ^1.4.0 = any 1.x at least 1.4.0).
A76: Concept 2 | B76: package-lock.json and uv.lock record the EXACT version of every package, including dependencies of dependencies. Commit lockfiles.
A77: Concept 3 | B77: Install from the lockfile in CI and production: 'npm ci' (not npm install) and 'uv sync --frozen'. They fail if the lockfile is out of date instead of silently upgrading.
A78: Concept 4 | B78: Dev dependencies (pytest, vitest, ruff, playwright) are needed to build and test, not to run in production.
A79: Concept 5 | B79: Semantic versioning: MAJOR.MINOR.PATCH. A major bump may break your code (react-chessboard 4 -> 5 changed its props API completely; we pin major version 4).
A80: Concept 6 | B80: uv is a fast Python package and project manager. 'uv add fastapi' edits pyproject.toml, resolves, writes uv.lock and installs into .venv. 'uv run <cmd>' runs a command inside that environment.
A81: Concept 7 | B81: For Docker we export a plain requirements.txt from the lockfile ('uv export --frozen --no-dev --no-emit-project -o requirements.txt') so the image needs only pip.
A82: In ChessLab | B82: apps/web/package-lock.json and services/backend/uv.lock are committed. CI uses npm ci and uv sync --frozen. When a library's latest major version changes its API, pin the major you learned (react-chessboard@4, react-router-dom@6).
A83: Common mistake | B83: Deleting the lockfile to 'fix' an install error (this upgrades everything at once).
A84: Common mistake | B84: Installing a package globally instead of into the project.
A85: Common mistake | B85: Using 'npm install' in CI, which can rewrite the lockfile.
... A93: L05 | B93: TypeScript essentials for this project · Beginner · about 90 min · used in P4, P9, P10
B94: ↑ back to Lessons index
A95: Why it matters | B95: TypeScript catches mistakes (wrong property names, missing fields, null values) before you run the code. API response types make the frontend/backend contract explicit.
A96: Concept 1 | B96: TypeScript = JavaScript + type annotations. 'let fen: string', 'function f(n: number): boolean'. Types are erased at build time; the browser runs plain JavaScript.
A97: Concept 2 | B97: Object types: type GameCreated = { game_id: string; analysis_job_id: number }. Optional fields use '?', nullable ones 'string | null'.
A98: Concept 3 | B98: Union types describe a fixed set of values: type Side = 'w' | 'b'. The compiler rejects 'x'.
A99: Concept 4 | B99: Generics: api<T>(path) returns Promise<T>, so api<Review>('/v1/...') is typed as a Review.
A100: Concept 5 | B100: async/await: fetch() returns a Promise; 'await' waits for it without freezing the page. Wrap awaits in try/catch to handle network errors.
A101: Concept 6 | B101: Narrowing: if (e instanceof ApiError) { e.code } — TypeScript knows e is an ApiError inside the if.
A102: Concept 7 | B102: Strict mode (on by default in Vite) forbids implicit any and forces null checks. Fix errors, don't silence them with 'as any'.
A103: Concept 8 | B103: The '!' non-null assertion tells TypeScript 'trust me'. Use it sparingly (e.g. document.getElementById('root')!).
A104: In ChessLab | B104: src/api/types.ts mirrors the backend's Pydantic models. If the backend renames a field, update this file and the compiler will show every place that needs changing. Optional upgrade: generate the types from FastAPI's /openapi.json with openapi-typescript.
A105: Common mistake | B105: Using 'any' to silence errors: you lose all protection.
A106: Common mistake | B106: Assuming fetch throws on 404: it does not. Our api() helper checks res.ok and throws ApiError.
... A115: L06 | B115: React fundamentals: components, props, state, effects and refs · Beginner · about 150 min · used in P4, P9, P10, P11
B116: ↑ back to Lessons index
A117: Why it matters | B117: React turns 'what the screen should look like for this data' into DOM updates. Every page of ChessLab is a React component.
A118: Concept 1 | B118: A component is a function that returns JSX (HTML-like syntax): function MoveList({ sans }) { return <table>...</table>; }. Props are its inputs.
A119: Concept 2 | B119: State (useState) is data that, when changed, re-renders the component: const [fen, setFen] = useState(START_FEN). Never mutate state directly; call the setter with a new value.
A120: Concept 3 | B120: Rendering must be pure: given the same props/state, return the same JSX. No fetches, timers or Date.now() during render (that is why PlayPage computes today's date once with useState(() => ...)).
A121: Concept 4 | B121: Effects (useEffect) synchronize with the outside world AFTER render: fetch data, start a Web Worker, set a timer. Return a cleanup function to stop it (terminate the worker, clear the timer). The dependency array says when to re-run.
A122: Concept 5 | B122: Refs (useRef) hold a mutable value that survives re-renders WITHOUT causing one: the chess.js object, the Stockfish worker, a 'current game id'. Read/write refs in effects and event handlers, not during render.
A123: Concept 6 | B123: Derived values: compute from state instead of storing duplicates (e.g. 'engineToMove' is derived from fen and status).
A124: Concept 7 | B124: Keys: lists need a stable key per item; giving a component a new key (PracticeSessionView key={sessionId}) creates a fresh instance with fresh state.
A125: Concept 8 | B125: StrictMode (development only) renders twice and runs effects twice on purpose, to reveal bugs. In ChessLab it revealed a real backend race condition (lesson L30).
A126: Concept 9 | B126: Custom hooks (useChessGame, usePolling) package reusable stateful logic. Their names must start with 'use'.
A127: In ChessLab | B127: useChessGame keeps the mutable chess.js instance in a ref and exposes render-safe state ('view'). PlayPage, ReviewView and PracticePage are components; App.tsx maps URLs to components with React Router.
A128: Common mistake | B128: Calling setState in a loop or during render (infinite re-render).
... A141: L07 | B141: Vite, dev servers and production builds · Beginner · about 30 min · used in P2, P4, P5
B142: ↑ back to Lessons index
A143: Why it matters | B143: You need to know what runs on your laptop during development versus what is deployed, and why environment variables in the frontend are public.
A144: Concept 1 | B144: 'npm run dev' starts Vite's development server with hot reload: save a file and the page updates instantly.
A145: Concept 2 | B145: 'npm run build' type-checks (tsc -b) and produces static files in dist/ (index.html, JS and CSS bundles with hashed names). Vercel serves these files; there is no Node server in production.
A146: Concept 3 | B146: public/ files are copied as-is to the site root: public/stockfish/x.js is served at /stockfish/x.js. Large binary assets like .wasm belong there.
A147: Concept 4 | B147: Environment variables: only variables starting with VITE_ are exposed to frontend code via import.meta.env.VITE_API_BASE_URL, and they are BAKED INTO the bundle at build time. Changing one in Vercel requires a rebuild. Never put a secret in a VITE_ variable.
A148: Concept 5 | B148: Client-side routing: the server has only index.html; React Router reads the URL in the browser. A direct visit to /review/123 must still return index.html, which is what the SPA rewrite in vercel.json does.
A149: In ChessLab | B149: vite.config.ts fixes the dev port at 5180 (5173 is used by another project on this machine). apps/web/.env.local holds VITE_API_BASE_URL=http://localhost:8010 for development; Vercel holds the production value.
A150: Common mistake | B150: Expecting process.env in browser code (Vite uses import.meta.env).
A151: Common mistake | B151: Forgetting the SPA rewrite: deep links return 404 in production.
A152: Common mistake | B152: Putting an API key in VITE_ANTHROPIC_KEY.
A153: Check yourself | B153: What is inside dist/ after a build?
A154: Check yourself | B154: Why must you redeploy the frontend after changing VITE_API_BASE_URL?
... A160: L08 | B160: Web Workers: keeping the page responsive while an engine thinks · Intermediate · about 40 min · used in P4
...

Sheet Code Index
A1: ID | B1: File path (relative to repo root) | C1: Phase | D1: What it is for | E1: Lines | F1: Open
A2: C01 | B2: .gitignore | C2: G0 | D2: Keeps Office lock files, dependencies, caches, secrets and large data out of Git. | E2: 21 | F2: View →
A3: C02 | B3: compose.yaml | C3: P2 | D3: Local stack: Postgres (5433), API (8010, runs migrations first), worker. | E3: 49 | F3: View →
A4: C03 | B4: services/backend/pyproject.toml | C4: P2 | D4: Backend dependencies (reference) and pytest/ruff settings. | E4: 30 | F4: View →
A5: C04 | B5: services/backend/.env.example | C5: P3 | D5: Every backend setting with safe local defaults. Copy to .env. | E5: 19 | F5: View →
A6: C05 | B6: services/backend/app/config.py | C6: P3 | D6: Typed settings from environment variables; fixes Render's postgres:// URL. | E6: 59 | F6: View →
A7: C06 | B7: services/backend/app/db.py | C7: P3 | D7: SQLAlchemy engine (bounded pool) and one session per request. | E7: 27 | F7: View →
A8: C07 | B8: services/backend/app/models.py | C8: P3 | D8: All 10 tables with database-level constraints. | E8: 220 | F8: View →
A9: C08 | B9: services/backend/migrations/env.py.additions | C9: P3 | D9: The 3 edits to Alembic's generated env.py. | E9: 13 | F9: View →
A10: C09 | B10: services/backend/app/errors.py | C10: P3 | D10: Uniform error JSON; tracebacks only in logs. | E10: 39 | F10: View →
A11: C10 | B11: services/backend/app/security.py | C11: P3 | D11: Guest tokens: generate, hash, authenticate, sliding expiry. | E11: 47 | F11: View →
A12: C11 | B12: services/backend/app/ratelimit.py | C12: P3 | D12: Small per-IP sliding-window rate limiter dependency. | E12: 37 | F12: View →
A13: C12 | B13: services/backend/app/api/sessions.py | C13: P3 | D13: POST /v1/sessions and GET /v1/me. | E13: 40 | F13: View →
... A94: C93 | B94: evaluation/compare_models.py | C94: S6 | D94: Constant vs Elo vs logistic regression on held-out attempts. | E94: 61 | F94: View →

Sheet Code
A1: Code library: every file below was written for this plan and (except deployment-only files) run and tested. Copy each file to the path shown in its header. Line numbers are for reference only; do not copy them.
A3: C01 | B3: .gitignore · Phase G0 · Keeps Office lock files, dependencies, caches, secrets and large data out of Git.
B4: ↑ back to Code Index
A5: 1 | B5: # Python
A6: 2 | B6: __pycache__/
A7: 3 | B7: *.pyc
A8: 4 | B8: .venv/
A9: 5 | B9: .pytest_cache/
A10: 6 | B10: .ruff_cache/
A11: 7 | B11: # Node
A12: 8 | B12: node_modules/
A13: 9 | B13: dist/
A14: 10 | B14: playwright-report/
A15: 11 | B15: test-results/
A16: 12 | B16: # Office lock files (Excel creates ~$name.xlsx while a workbook is open)
A17: 13 | B17: ~$*
A18: 14
A19: 15 | B19: # Secrets and local config
A20: 16 | B20: .env
A21: 17 | B21: .env.local
A22: 18 | B22: *.local
A23: 19 | B23: # Data: commit manifests and the small subset, never the full Lichess dump
A24: 20 | B24: *.csv.zst
A25: 21 | B25: data/raw/
A28: C02 | B28: compose.yaml · Phase P2 · Local stack: Postgres (5433), API (8010, runs migrations first), worker.
B29: ↑ back to Code Index
A30: 1 | B30: # Local stack: docker compose up --build
A31: 2 | B31: # db = Postgres, api = FastAPI on :8000, worker = job runner with Stockfish. The frontend runs with `npm run dev`.
A32: 3 | B32: services:
A33: 4 | B33: db:
A34: 5 | B34: image: postgres:16
A35: 6 | B35: environment:
A36: 7 | B36: POSTGRES_USER: chesslab
A37: 8 | B37: POSTGRES_PASSWORD: chesslab
A38: 9 | B38: POSTGRES_DB: chesslab
A39: 10 | B39: ports:
A40: 11 | B40: - "5433:5432" # host port 5433, because 5432 is often taken by another Postgres
A41: 12 | B41: volumes:
... A47: 18 | B47: retries: 20
A48: 19
A49: 20 | B49: api:
A50: 21 | B50: build: ./services/backend
A51: 22 | B51: environment:
A52: 23 | B52: DATABASE_URL: postgresql+psycopg://chesslab:chesslab@db:5432/chesslab
A53: 24 | B53: ALLOWED_ORIGINS: http://localhost:5180
A54: 25 | B54: ports:
A55: 26 | B55: - "8010:8000" # http://localhost:8010 on your machine
A56: 27 | B56: depends_on:
A57: 28 | B57: db:
A58: 29 | B58: condition: service_healthy
A59: 30 | B59: # Migrations run once here, before the API starts. The worker waits for the API to be healthy.
A60: 31 | B60: command: sh -c "alembic upgrade head && uvicorn app.main:app --host 0.0.0.0 --port 8000"
... A65: 36 | B65: retries: 20
A66: 37
A67: 38 | B67: worker:
A68: 39 | B68: build: ./services/backend
A69: 40 | B69: environment:
A70: 41 | B70: DATABASE_URL: postgresql+psycopg://chesslab:chesslab@db:5432/chesslab
A71: 42 | B71: depends_on:
A72: 43 | B72: api:
A73: 44 | B73: condition: service_healthy
A74: 45 | B74: command: python -m app.worker
A75: 46 | B75: stop_grace_period: 30s # time to finish the current job after SIGTERM
A76: 47
A77: 48 | B77: volumes:
A78: 49 | B78: pgdata:
A81: C03 | B81: services/backend/pyproject.toml · Phase P2 · Backend dependencies (reference) and pytest/ruff settings.
B82: ↑ back to Code Index
A83: 1 | B83: # Created by `uv init` and filled by the `uv add` commands in Phase 2. Shown here for reference:
A84: 2 | B84: # your file will contain the exact versions uv resolved, and uv.lock pins every transitive package.
A85: 3 | B85: [project]
A86: 4 | B86: name = "chesslab-backend"
A87: 5 | B87: version = "0.1.0"
A88: 6 | B88: requires-python = ">=3.12"
A89: 7 | B89: dependencies = [
A90: 8 | B90: "alembic>=1.13",
A91: 9 | B91: "chess>=1.11",
A92: 10 | B92: "fastapi>=0.115",
A93: 11 | B93: "httpx>=0.27",
A94: 12 | B94: "psycopg[binary]>=3.2",
... A99: 17 | B99: ]
A100: 18
A101: 19 | B101: [dependency-groups]
A102: 20 | B102: dev = ["pytest>=8", "ruff>=0.6", "zstandard>=0.23"]
A103: 21
A104: 22 | B104: [tool.pytest.ini_options]
A105: 23 | B105: pythonpath = ["."]
A106: 24 | B106: testpaths = ["tests"]
A107: 25
A108: 26 | B108: [tool.ruff]
A109: 27 | B109: line-length = 130
A110: 28
A111: 29 | B111: [tool.ruff.lint]
A112: 30 | B112: select = ["E", "F", "W", "I"]
A115: C04 | B115: services/backend/.env.example · Phase P3 · Every backend setting with safe local defaults. Copy to .env.
B116: ↑ back to Code Index
A117: 1 | B117: # Copy to .env for running the API/worker directly on your machine (outside Docker).
A118: 2 | B118: # Never commit .env. Production values live in Render's dashboard.
A119: 3 | B119: ENVIRONMENT=development
A120: 4 | B120: DATABASE_URL=postgresql+psycopg://chesslab:chesslab@localhost:5433/chesslab
...

Sheet API Reference
A1: Method | B1: Path | C1: Auth | D1: Request body | E1: Response | F1: Success | G1: Error codes
A2: POST | B2: /v1/sessions | C2: No (rate-limited) | D2: — | E2: {token, visitor_id, expires_at} | F2: 201 | G2: RATE_LIMITED
A3: GET | B3: /v1/me | C3: Bearer | D3: — | E3: {visitor_id, expires_at} | F3: 200 | G3: AUTH_REQUIRED, AUTH_INVALID
A4: POST | B4: /v1/games | C4: Bearer | D4: {pgn, player_color, engine_label} | E4: {game_id, analysis_job_id} | F4: 201 | G4: INVALID_PGN, VALIDATION_FAILED
A5: GET | B5: /v1/games | C5: Bearer | D5: — | E5: [GameSummary] | F5: 200
A6: GET | B6: /v1/games/{id} | C6: Bearer (owner) | D6: — | E6: GameDetail (pgn, initial_fen ...) | F6: 200 | G6: GAME_NOT_FOUND
A7: POST | B7: /v1/games/{id}/analysis | C7: Bearer (owner) | D7: — | E7: {game_id, analysis_job_id} | F7: 202 | G7: GAME_NOT_FOUND
A8: GET | B8: /v1/games/{id}/review | C8: Bearer (owner) | D8: — | E8: Review (state, coverage, findings[]) | F8: 200 | G8: GAME_NOT_FOUND
A9: GET | B9: /v1/demo/review | C9: No | D9: — | E9: Review (is_demo = true) | F9: 200 | G9: DEMO_MISSING
A10: POST | B10: /v1/imports | C10: Bearer | D10: {provider, username, max_games<=200} | E10: ImportRun | F10: 202 | G10: IMPORT_RATE_LIMITED, VALIDATION_FAILED
A11: POST | B11: /v1/imports/pgn | C11: Bearer | D11: multipart: file, player_name?, player_color | E11: {import_id, accepted, duplicates, errors[]} | F11: 202 | G11: UPLOAD_TOO_LARGE
A12: GET | B12: /v1/imports/{id} | C12: Bearer (owner) | D12: — | E12: ImportRun (fetched, eligible, excluded, analyzed) | F12: 200 | G12: IMPORT_NOT_FOUND
A13: GET | B13: /v1/jobs/{id} | C13: Bearer (owner) | D13: — | E13: {status, attempts, progress, error_code} | F13: 200 | G13: JOB_NOT_FOUND
A14: POST | B14: /v1/jobs/{id}/cancel | C14: Bearer (owner) | D14: — | E14: {status} | F14: 200 | G14: JOB_NOT_FOUND
A15: POST | B15: /v1/practice/sessions | C15: Bearer | D15: {concept?, evidence_id?, mode} | E15: PracticeSession (no solution!) | F15: 201 | G15: NO_PUZZLE_AVAILABLE, EVIDENCE_NOT_FOUND
A16: GET | B16: /v1/practice/sessions/{id} | C16: Bearer (owner) | D16: — | E16: PracticeSession | F16: 200 | G16: SESSION_NOT_FOUND
A17: POST | B17: /v1/practice/sessions/{id}/moves | C17: Bearer (owner) | D17: {uci} | E17: {outcome, fen, opponent_reply_uci, state, first_try_success, rating_after} | F17: 200 | G17: ILLEGAL_MOVE, SESSION_FINISHED
... A19: POST | B19: /v1/practice/sessions/{id}/give-up | C19: Bearer (owner) | D19: — | E19: MoveResult (final position) | F19: 200 | G19: SESSION_FINISHED
A20: GET | B20: /v1/progress | C20: Bearer | D20: — | E20: {concepts[], note} | F20: 200
A21: DELETE | B21: /v1/me/data | C21: Bearer | D21: — | E21: (empty) | F21: 204
A22: GET | B22: /health/live | C22: No | D22: — | E22: {status: ok} | F22: 200
A23: GET | B23: /health/ready | C23: No | D23: — | E23: {status: ready, environment} | F23: 200 | G23: 500 if DB unreachable
A25: Error shape for every failure: {"error": {"code": "STABLE_CODE", "message": "Human text"}}. Interactive docs: http://localhost:8010/docs (and /docs on your Render URL).

Sheet Config & Env
A1: Variable | B1: Used by | C1: Local value | D1: Production value / where set | E1: Kind | F1: Notes
A2: DATABASE_URL | B2: API, worker | C2: postgresql+psycopg://chesslab:chesslab@localhost:5433/chesslab | D2: Render: from database (internal URL) | E2: Secret | F2: Contains the DB password. Never log it.
A3: ALLOWED_ORIGINS | B3: API | C3: http://localhost:5180 | D3: https://<project>.vercel.app | E3: Config | F3: Comma-separated exact origins, no trailing slash.
A4: ENVIRONMENT | B4: API, worker | C4: development | D4: production | E4: Config | F4: Shown by /health/ready.
A5: SESSION_TTL_DAYS | B5: API | C5: 30 | D5: 30 | E5: Config | F5: Sliding guest expiry.
A6: STOCKFISH_PATH | B6: Worker | C6: stockfish | D6: /usr/games/stockfish (set in Dockerfile) | E6: Config | F6: Never user-controlled.
A7: ENGINE_THREADS | B7: Worker | C7: 1 | D7: 1 | E7: Config | F7: Keep 1 on small instances.
A8: ENGINE_HASH_MB | B8: Worker | C8: 32 | D8: 32 | E8: Config | F8: Memory per engine.
A9: ANALYSIS_DEPTH | B9: Worker | C9: 14 | D9: 14 | E9: Config | F9: Part of the evidence record; changing it changes results.
A10: ANALYSIS_TIME_S | B10: Worker | C10: 0.5 | D10: 0.5 | E10: Config | F10: Per evaluated move.
A11: MAX_CANDIDATES_PER_POSITION | B11: Worker | C11: 3 | D11: 3 | E11: Config | F11: Budget.
A12: MAX_IMPORT_GAMES | B12: API | C12: 200 | D12: 200 | E12: Config | F12: Upper bound per import.
... A16: WORKER_POLL_SECONDS | B16: Worker | C16: 1.0 | D16: 1.0 | E16: Config | F16: Sleep when queue is empty.
A17: LOG_LEVEL | B17: API, worker | C17: INFO | D17: INFO | E17: Config
A18: LLM_REWORDING_ENABLED | B18: Worker (S3) | C18: false | D18: false until evaluated | E18: Config | F18: Feature flag.
A19: ANTHROPIC_MODEL | B19: Worker (S3) | C19: claude-opus-5-5 | D19: your measured choice | E19: Config | F19: Model id for rewording.
A20: ANTHROPIC_API_KEY | B20: Worker (S3) | C20: (local .env only) | D20: Render secret | E20: Secret | F20: Never in the frontend or Git.
A21: PORT | B21: API | C21: (set by uvicorn command) | D21: Set by Render automatically | E21: Platform | F21: API must bind 0.0.0.0:$PORT.
A22: VITE_API_BASE_URL | B22: Frontend build | C22: http://localhost:8010 | D22: https://<api>.onrender.com | E22: PUBLIC | F22: Baked into the JS bundle at build time.
A24: Local port | B24: Value | C24: Why
A25: Postgres (Docker, host side) | B25: 5433 | C25: 5432 is used by another project's Postgres on this machine (tomi-ren-postgres-1).
A26: API (Docker, host side) | B26: 8010 | C26: 8000 is used by fastapi-iam on this machine.
A27: Web dev server (Vite) | B27: 5180 | C27: 5173 is used by another Vite app (TomiRen) on this machine.
A28: Inside Docker network | B28: db:5432, api:8000 | C28: Containers talk to each other on internal ports by service name.

Sheet Checklists
A1: Area | B1: Check | C1: Task | D1: Status (edit) | E1: Evidence / notes (edit)
A2: Security | B2: A second guest gets 404 for the first guest's game, review, job and cancel endpoints | C2: P13.01 | D2: Not started
A3: Security | B3: Upload over 2 MB returns 413; >200 games are truncated; >400-ply games rejected | C3: P13.01 | D3: Not started
A4: Security | B4: Invalid username returns 422; only lichess.org / api.chess.com are ever fetched | C4: P13.01 | D4: Not started
A5: Security | B5: Second simultaneous import returns 429; 11 session creations/min per IP return 429 | C5: P13.01 | D5: Not started
A6: Security | B6: No traceback or SQL in any error response | C6: P13.01 | D6: Not started
A7: Security | B7: No tokens, DATABASE_URL or API keys in logs (search Render logs) | C7: P13.05 | D7: Not started
A8: Security | B8: Containers run as non-root (whoami -> appuser) | C8: P13.01 | D8: Not started
A9: Security | B9: CSP active; no violations in console; no dangerouslySetInnerHTML | C9: P13.02 | D9: Not started
A10: Security | B10: ALLOWED_ORIGINS is the exact Vercel origin (no '*') | C10: P5.09 | D10: Not started
A11: Privacy | B11: 'Delete my data' removes everything and invalidates the token | C11: P13.03 | D11: Not started
A12: Privacy | B12: Expired guests deleted by the hourly cleanup | C12: P13.03 | D12: Not started
A13: Privacy | B13: Demo clearly labelled as a sample; never mixed with private history | C13: P9.06 | D13: Not started
... A41: Engineering | B41: Both of you can push to main from your own laptop, and CI is green on the latest commit | C41: P5.05 | D41: Not started
B43: Checks done | D43: =COUNTIF(D2:D41,"Done")&" / "&COUNTIF(B2:B41,"*")

Sheet Troubleshooting
A1: Area | B1: Symptom | C1: Likely cause | D1: Fix
A2: Setup | B2: 'uv' (or 'node') is not recognized | C2: The installer changed PATH but your terminal started before. | D2: Close and reopen the terminal (and VS Code). Check with 'uv --version'.
A3: Setup | B3: docker: 'Cannot connect to the Docker daemon' / engine not running | C3: Docker Desktop is closed or WSL2 is not ready. | D3: Start Docker Desktop and wait for 'Engine running'. Run 'wsl --status'; enable WSL2 integration in Docker settings.
A4: Setup | B4: 'port is already allocated' when starting Compose | C4: Another program uses the port. On this machine 5432, 5434, 8000, 8080 and 5173 are already used by other projects. | D4: Use ChessLab's ports (5433, 8010, 5180). Find the owner with 'docker ps --format "{{.Names}} {{.Ports}}"' or 'netstat -ano | findstr :5433'.
A5: Setup | B5: Playwright tests interact with a different website | C5: reuseExistingServer reused another app already running on the same port (happened during verification on port 5173). | D5: Use the dedicated port 5180 with strictPort, and stop other dev servers.
A6: Setup | B6: Git Bash turns /usr/games/stockfish into C:/Program Files/Git/usr/games/stockfish | C6: MSYS path conversion rewrites Unix-looking arguments passed to Windows programs. | D6: Run docker commands in PowerShell, or prefix them with MSYS_NO_PATHCONV=1 in Git Bash.
A7: Python | B7: ModuleNotFoundError: No module named 'app' | C7: Command run from the wrong folder or without the project environment. | D7: cd services/backend and use 'uv run ...'. For pytest make sure pyproject.toml has pythonpath = ['.'].
A8: Python | B8: Library fails to install on Python 3.14 | C8: Very new Python versions may lack pre-built wheels. | D8: Use Python 3.12 for the project: 'uv python install 3.12' and 'uv init --python 3.12' (or 'uv python pin 3.12').
A9: Python | B9: pytest errors with connection refused / 5 errors before any test runs | C9: The test database is not reachable (conftest connects at startup). | D9: Start Postgres ('docker compose up -d db'); check DATABASE_URL points at localhost:5433/chesslab_test.
A10: Python | B10: Warning: Using httpx with starlette.testclient is deprecated; install httpx2 | C10: Newer Starlette versions prefer the httpx2 package for TestClient. | D10: Harmless for now; optionally 'uv add --dev httpx2'. Don't remove httpx: the importers use it.
A11: Database | B11: sqlalchemy.exc.NoSuchModuleError: postgres | C11: Render gives 'postgres://' URLs; SQLAlchemy needs a dialect and driver. | D11: Settings.use_psycopg_driver converts it to postgresql+psycopg://. Make sure config.py has the validator.
A12: Database | B12: alembic autogenerate produces an empty migration | C12: env.py doesn't import your models or uses the wrong metadata. | D12: Add 'import app.models' and target_metadata = Base.metadata (Code: env.py.additions).
... A50: Docker | B50: 'the input device is not a TTY' after docker compose exec ... psql | C50: Git Bash's default window (mintty) is not a Windows console. | D50: Prefix with winpty (winpty docker compose exec db psql ...), or use -T for non-interactive commands.

Sheet Glossary
A1: Term | B1: Meaning | C1: Lesson
A2: Alembic | B2: Python tool that applies versioned database schema migrations. | C2: L17
A3: Alpha-beta pruning | B3: Search optimisation that skips branches which cannot change the minimax result. | C3: L10
A4: API | B4: Application Programming Interface: here, the HTTP endpoints the frontend calls. | C4: L12
A5: ApiError | B5: ChessLab's exception carrying an HTTP status, a stable code and a human message. | C5: L22
A6: At-least-once delivery | B6: A job may run more than once (after crashes); handlers must therefore be idempotent. | C6: L28
A7: Backoff (exponential) | B7: Waiting longer after each failed retry (5 s, 10 s, 20 s ...). | C7: L29
A8: Bearer token | B8: A credential sent as 'Authorization: Bearer <token>'; whoever holds it is authenticated. | C8: L19
A9: BKT | B9: Bayesian Knowledge Tracing: a model of whether a learner has mastered a skill. | C9: L57
A10: Brier score | B10: Mean squared error of probability predictions; lower is better. | C10: L46
A11: Calibration | B11: Whether predicted probabilities match observed frequencies. | C11: L46
A12: Candidate (fork candidate) | B12: A geometric knight move that attacks 2+ worthwhile targets; not yet verified. | C12: L38
... A118: WSL2 | B118: Windows Subsystem for Linux; Docker Desktop runs Linux containers in it. | C118: L15

Sheet Resources
A1: Lesson | B1: Lesson title | C1: Resource | D1: Link (click)
A2: L01 | B2: How the web works: browsers, servers, HTTP and JSON | C2: MDN: An overview of HTTP | D2: https://developer.mozilla.org/en-US/docs/Web/HTTP/Overview
A3: L01 | B3: How the web works: browsers, servers, HTTP and JSON | C3: MDN: HTTP response status codes | D3: https://developer.mozilla.org/en-US/docs/Web/HTTP/Status
A4: L01 | B4: How the web works: browsers, servers, HTTP and JSON | C4: MDN: Learn web development | D4: https://developer.mozilla.org/en-US/docs/Learn_web_development
A5: L01 | B5: How the web works: browsers, servers, HTTP and JSON | C5: Full Stack Open (free university course) | D5: https://fullstackopen.com/en/
A6: L02 | B6: The terminal on Windows: Git Bash, paths and environment variables | C6: Git for Windows (includes Git Bash) | D6: https://gitforwindows.org/
A7: L02 | B7: The terminal on Windows: Git Bash, paths and environment variables | C7: The Missing Semester (MIT): the shell | D7: https://missing.csail.mit.edu/2020/course-shell/
A8: L02 | B8: The terminal on Windows: Git Bash, paths and environment variables | C8: GNU Bash manual | D8: https://www.gnu.org/software/bash/manual/bash.html
A9: L02 | B9: The terminal on Windows: Git Bash, paths and environment variables | C9: VS Code: integrated terminal profiles | D9: https://code.visualstudio.com/docs/terminal/profiles
A10: L03 | B10: Git and GitHub: commits, branches, pull requests | C10: Pro Git book (free) | D10: https://git-scm.com/book/en/v2
A11: L03 | B11: Git and GitHub: commits, branches, pull requests | C11: Learn Git Branching (interactive) | D11: https://learngitbranching.js.org/
A12: L03 | B12: Git and GitHub: commits, branches, pull requests | C12: GitHub Docs: About pull requests | D12: https://docs.github.com/en/pull-requests/collaborating-with-pull-requests/proposing-changes-to-your-work-with-pull-requests/about-pull-requests
... A182: L59 | B182: Sharing one repository as two people: pull, commit, push and fixing conflicts | C182: Learn Git Branching (interactive) | D182: https://learngitbranching.js.org/

Sheet Interview Prep
A1: Topic | B1: Question | C1: Answer outline (say it in your own words) | D1: Practised (edit)
A2: Architecture | B2: Walk me through ChessLab's architecture. | C2: Browser (React, Stockfish WASM in a worker for play) -> FastAPI (validation, auth, ownership) -> Postgres (data AND job queue) <- Python worker (python-chess + native Stockfish for analysis and imports). Vercel serves the static frontend; Render runs API, worker and Postgres. | D2: Not started
A3: Architecture | B3: Why does the game run in the browser instead of on the server? | C3: Single-player vs engine has nothing to cheat at, so server authority adds cost and latency without benefit. The server re-validates the finished PGN before trusting it, which is where trust matters (analysis, practice, ratings). | D3: Not started
A4: Architecture | B4: Why use Postgres as a queue instead of Redis/RabbitMQ? | C4: One less service to run and pay for, transactional enqueue together with the data, durability, and SKIP LOCKED gives safe concurrent claiming. At ChessLab's scale it is more than enough; I'd revisit at very high throughput. | D4: Not started
A5: Queue | B5: Explain FOR UPDATE SKIP LOCKED. | C5: FOR UPDATE locks the chosen row; SKIP LOCKED makes other workers skip locked rows instead of waiting. In one UPDATE ... WHERE id = (SELECT ... FOR UPDATE SKIP LOCKED LIMIT 1) each worker claims a different job atomically. A test with 4 threads and 30 jobs proved no duplicates. | D5: Not started
A6: Queue | B6: What happens if a worker crashes mid-job? | C6: Its lease (60 s, extended by heartbeats) expires; another worker reclaims the job with attempts+1. Handlers are idempotent (delete-and-rewrite evidence, ON CONFLICT inserts), so re-running is safe. A stale worker's late update is fenced out by matching attempts. | D6: Not started
A7: Queue | B7: How do you prevent a 200-game import from delaying a user's just-finished game? | C7: One job per game, priority 10 for interactive vs 0 for imports, plus aging (priority grows with waiting time) so imports are not starved. | D7: Not started
A8: Reliability | B8: Give an example of idempotency in your system. | C8: Saving a played game uses a unique (owner, source, fingerprint) constraint and ON CONFLICT DO NOTHING, and enqueue uses a dedupe key: double clicks return the same game and one job. Rating updates use UPDATE ... WHERE rating_applied = false. | D8: Not started
A9: Reliability | B9: Tell me about a bug you found. | C9: React StrictMode fired two simultaneous 'start practice' requests; both tried to create the concept rating row and one failed with a UniqueViolation (500). Fixed with INSERT ... ON CONFLICT DO NOTHING + SELECT, a row lock for updates, and a concurrent regression test. | D9: Not started
A10: AI | B10: Where is the AI in this project? | C10: Stockfish provides search-based playing strength (integrated). My detector is a hybrid: rule-based candidate generation plus engine verification. The learner model is a per-concept Elo that predicts success and drives adaptive selection. An optional LLM only rewrites verified explanations. And the evaluation pipeline measures all of it. | D10: Not started
A11: AI | B11: How does the fork detector avoid false positives? | C11: Two stages: cheap geometric candidates (legal knight moves attacking 2+ worthwhile targets), then verification: engine scores the candidate and the played move with identical limits; the PV must be legal, capture a forked target and net >= 2 pawns (or mate), and beat the played move by >= 150 cp. Negative tests cover pinned knights, defended targets, capturable knights and equal alternatives. | D11: Not started
A12: AI | B12: Why not let an LLM explain the mistakes? | C12: LLMs can state plausible but false chess. Evidence records are verified facts; deterministic templates render them. An optional LLM may rephrase, constrained by structured output and guards that reject unknown moves or numbers, with the template as fallback. | D12: Not started
... A32: Teamwork | B32: How did the two of you split the work? | C32: Every step had one owner, balanced by hours in every chapter, so each of us built part of every layer: frontend, backend, queue, AI and deployment. We shared one repository, pulled before each step, pushed small commits named after the step, and skimmed each other's commits to learn the other half. | D32: Not started

Sheet Decisions
A1: Topic | B1: PROJECT_PLAN.md | C1: This plan | D1: Why
A2: Where the game is played | B2: Server-authoritative game loop with engine-turn jobs | C2: Browser plays the game (Stockfish WASM in a worker); the server re-validates the finished PGN | D2: Nothing to cheat at in single-player; removes engine-turn jobs, revision races and server CPU per move; trust is enforced where it matters (stored games, analysis, practice).
A3: Definition of 'done' for the portfolio | B3: All 14 sections incl. Chess.com, hanging pieces, engine comparison, pilot | C3: Core = P0-P14 (one concept done well, Lichess + PGN, full learning loop, evaluation, ops, docs); the rest are Stretch phases S1-S7 | D3: About 80% of the portfolio value for far less effort; stretch phases are fully specified when you want them.
A4: Job queue | B4: Postgres jobs table with leases | C4: Same (kept), plus fencing via attempts, priority aging, exhausted-lease sweep | D4: Same reasoning as the plan; additions verified by tests.
A5: Server engine | B5: Pinned Stockfish binary/network | C5: Debian package stockfish in python:3.12-slim-bookworm (verified: Stockfish 15.1) | D5: Simplest reproducible Linux build; upgrade path documented.
A6: Frontend board | B6: Any maintained board component | C6: react-chessboard 4.x (MIT), chess.js 1.x, React Router 6.x | D6: Versions verified together with React 19 and Vite 8 in this plan's test run.
A7: Explanations | B7: Deterministic templates first, LLM optional | C7: Same; LLM stretch uses Claude with structured outputs + guards + template fallback | D7: LLM is a writer, not a judge.
A8: Local ports | B8: Defaults (5432/8000/5173) | C8: 5433/8010/5180 | D8: Defaults collide with other projects running on this machine.
A9: Python version | B9: Unspecified | C9: 3.12 via uv | D9: Widest wheel support; 3.14 on this machine is very new.
A10: Terminal | B10: PowerShell commands | C10: Git Bash commands everywhere; MSYS_NO_PATHCONV=1 on docker commands with container paths | D10: Same shell as Linux servers, Docker and CI; one syntax for both laptops.
A11: Version control | B11: One branch, occasional commits | C11: One shared repository (msris93197-dev/ChessLab); pull --rebase, commit, push straight to main after every step that changes files | D11: Two people, finishing fast: no branches, pull requests or journals to manage.
A12: Team | B12: One builder | C12: Every step owned by Srikanth or Siva prasad (Both only for per-laptop installs and the pilot), balanced by hours in each chapter | D12: Equal share of the work across every layer of the app.
